Workbook

Sheet Data
A1: Date | B1: BoE 3Y OIS (%) | C1: BoE 3Y implied real spot (%) | D1: BoE 3Y Spot (%) | E1: BoE 10Y Spot (%) | F1: BoE 20Y Spot (%) | G1: Interpolated 5.56Y Yield (%) | H1: iShares Core £ Corp Bond (SLXX) (%) | I1: iShares Global HY Corp Bond ETF GBP Hedged (GHYS.L) (%) | J1: S&P 500 Price | K1: S&P 500 Returns (%) | L1: S&P 500 Earnings | M1: S&P 500 E/P | N1: Effective Federal Funds Rate (monthly) (%) | O1: Asset Returns (%) | P1: Slope (20Y-3Y) (%) | Q1: Butterfly (2x10Y-20Y-3Y) (%) | R1: Average SONIA (%) | S1: SONIA - EFFR (%) | T1: 3Y Gilt - 3Y OIS (%) | U1: Slope Change (%) | V1: Butterfly Change (%) | W1: IG Credit Spread (%) | X1: HY-IG Spread (%) | Y1: S&P 500 Returns - HY (%) | Z1: Inflation (3Y gilt - 3Y IL) (%) | AA1: Inflation Change (%) | AB1: VIX (Close) | AC1: Change in VIX (%) | AD1: S&P 500 ERP GBP Hedged (%)
A2: 41426 | B2: 0.052583709 | C2: -0.13666667 | D2: 0.060833333 | E2: 0.21833333 | F2: 0.29416667 | G2: =0.3657*E2+(1-0.3657)*D2 -> 0.11843108 | H2: -5.0202884 | I2: 0.92171578 | J2: 1618.77 | K2: =AVERAGE(K3:K145) -> 0.010751403 | L2: 90.95 | M2: =L2/J2 -> 0.056184634 | N2: 0.0075 | O2: -3.1231512 | P2: =F2-D2 -> 0.23333333 | Q2: =2*E2-F2-D2 -> 0.081666667 | R2: 0.035433333 | S2: =R2-N2 -> 0.027933333 | T2: =D2-B2 -> 0.0082496246 | U2: =AVERAGE(U3:U145) -> -0.00074009324 | V2: =AVERAGE(V3:V145) -> -0.00046037296 | W2: =H2-G2 -> -5.1387194 | X2: =I2-H2 -> 5.9420041 | Y2: =K2-I2 -> -0.91096438 | Z2: =D2-C2 -> 0.1975 | AA2: =AVERAGE(AA3:AA145) -> 0.00036713287 | AB2: 16.86 | AC2: 3.5626536 | AD2: =M2-N2 -> 0.048684634
A3: 41456 | B3: 0.044828492 | C3: -0.1675 | D3: 0.05 | E3: 0.21333333 | F3: 0.295 | G3: =0.3657*E3+(1-0.3657)*D3 -> 0.109731 | H3: 2.4581801 | I3: 2.4288457 | J3: 1668.68 | K3: =-1+J3/J2 -> 0.030832051 | L3: =L2*2/3+L5/3 -> 92.09 | M3: =L3/J3 -> 0.055187334 | N3: 0.0075 | O3: 3.4388142 | P3: =F3-D3 -> 0.245 | Q3: =2*E3-F3-D3 -> 0.081666667 | R3: 0.035841667 | S3: =R3-N3 -> 0.028341667 | T3: =D3-B3 -> 0.0051715084 | U3: =P3-P2 -> 0.011666667 | V3: =Q3-Q2 -> 0 | W3: =H3-G3 -> 2.3484491 | X3: =I3-H3 -> -0.029334478 | Y3: =K3-I3 -> -2.3980136 | Z3: =D3-C3 -> 0.2175 | AA3: =Z3-Z2 -> 0.02 | AB3: 13.45 | AC3: -16.975309 | AD3: =M3-N3 -> 0.047687334
A4: 41487 | B4: 0.064357428 | C4: -0.15833333 | D4: 0.069166667 | E4: 0.23583333 | F4: 0.30333333 | G4: =0.3657*E4+(1-0.3657)*D4 -> 0.13011667 | H4: -0.79307812 | I4: -0.74915777 | J4: 1670.09 | K4: =-1+J4/J3 -> 0.00084497927 | L4: =L2/3+L5*2/3 -> 93.23 | M4: =L4/J4 -> 0.055823339 | N4: 0.0066666667 | O4: -1.8423177 | P4: =F4-D4 -> 0.23416667 | Q4: =2*E4-F4-D4 -> 0.099166667 | R4: 0.035583333 | S4: =R4-N4 -> 0.028916667 | T4: =D4-B4 -> 0.0048092386 | U4: =P4-P3 -> -0.010833333 | V4: =Q4-Q3 -> 0.0175 | W4: =H4-G4 -> -0.92319479 | X4: =I4-H4 -> 0.04392035 | Y4: =K4-I4 -> 0.75000275 | Z4: =D4-C4 -> 0.2275 | AA4: =Z4-Z3 -> 0.01 | AB4: 17.01 | AC4: 43.665541 | AD4: =M4-N4 -> 0.049156672
A5: 41518 | B5: 0.067847311 | C5: -0.15666667 | D5: 0.071666667 | E5: 0.23 | F5: 0.295 | G5: =0.3657*E5+(1-0.3657)*D5 -> 0.12956917 | H5: 0.95391684 | I5: 1.2471351 | J5: 1687.17 | K5: =-1+J5/J4 -> 0.010226994 | L5: 94.37 | M5: =L5/J5 -> 0.055933901 | N5: 0.0066666667 | O5: 0.76476526 | P5: =F5-D5 -> 0.22333333 | Q5: =2*E5-F5-D5 -> 0.093333333 | R5: 0.035825 | S5: =R5-N5 -> 0.029158333 | T5: =D5-B5 -> 0.0038193557 | U5: =P5-P4 -> -0.010833333 | V5: =Q5-Q4 -> -0.0058333333 | W5: =H5-G5 -> 0.82434768 | X5: =I5-H5 -> 0.2932183 | Y5: =K5-I5 -> -1.2369081 | Z5: =D5-C5 -> 0.22833333 | AA5: =Z5-Z4 -> 0.00083333333 | AB5: 16.6 | AC5: -0.060204696 | AD5: =M5-N5 -> 0.049267234
A6: 41548 | B6: 0.064237813 | C6: -0.16666667 | D6: 0.069166667 | E6: 0.225 | F6: 0.29083333 | G6: =0.3657*E6+(1-0.3657)*D6 -> 0.12615492 | H6: 2.1513665 | I6: 2.4954859 | J6: 1720.03 | K6: =-1+J6/J5 -> 0.019476401 | L6: =L5*2/3+L8/3 -> 96.313333 | M6: =L6/J6 -> 0.055995147 | N6: 0.0075 | O6: 2.8438546 | P6: =F6-D6 -> 0.22166667 | Q6: =2*E6-F6-D6 -> 0.09 | R6: 0.035941667 | S6: =R6-N6 -> 0.028441667 | T6: =D6-B6 -> 0.004928854 | U6: =P6-P5 -> -0.0016666667 | V6: =Q6-Q5 -> -0.0033333333 | W6: =H6-G6 -> 2.0252116 | X6: =I6-H6 -> 0.34411937 | Y6: =K6-I6 -> -2.4760095 | Z6: =D6-C6 -> 0.23583333 | AA6: =Z6-Z5 -> 0.0075 | AB6: 13.75 | AC6: -17.86141 | AD6: =M6-N6 -> 0.048495147
A7: 41579 | B7: 0.067238377 | C7: -0.15333333 | D7: 0.075 | E7: 0.24 | F7: 0.30416667 | G7: =0.3657*E7+(1-0.3657)*D7 -> 0.1353405 | H7: -1.2729617 | I7: 0.038646518 | J7: 1783.54 | K7: =-1+J7/J6 -> 0.036923775 | L7: =L5/3+L8*2/3 -> 98.256667 | M7: =L7/J7 -> 0.055090812 | N7: 0.0066666667 | O7: -0.40587404 | P7: =F7-D7 -> 0.22916667 | Q7: =2*E7-F7-D7 -> 0.10083333 | R7: 0.035833333 | S7: =R7-N7 -> 0.029166667 | T7: =D7-B7 -> 0.007761623 | U7: =P7-P6 -> 0.0075 | V7: =Q7-Q6 -> 0.010833333 | W7: =H7-G7 -> -1.4083022 | X7: =I7-H7 -> 1.3116082 | Y7: =K7-I7 -> -0.0017227431 | Z7: =D7-C7 -> 0.22833333 | AA7: =Z7-Z6 -> -0.0075 | AB7: 13.7 | AC7: 3.1626506 | AD7: =M7-N7 -> 0.048424145
A8: 41609 | B8: 0.094568324 | C8: -0.14166667 | D8: 0.098333333 | E8: 0.26333333 | F8: 0.31083333 | G8: =0.3657*E8+(1-0.3657)*D8 -> 0.15867383 | H8: -0.73664307 | I8: 0.74090576 | J8: 1807.78 | K8: =-1+J8/J7 -> 0.013590948 | L8: 100.2 | M8: =L8/J8 -> 0.055427098 | N8: 0.0075 | O8: 0.3946379 | P8: =F8-D8 -> 0.2125 | Q8: =2*E8-F8-D8 -> 0.1175 | R8: 0.035125 | S8: =R8-N8 -> 0.027625 | T8: =D8-B8 -> 0.0037650094 | U8: =P8-P7 -> -0.016666667 | V8: =Q8-Q7 -> 0.016666667 | W8: =H8-G8 -> -0.8953169 | X8: =I8-H8 -> 1.4775488 | Y8: =K8-I8 -> -0.72731482 | Z8: =D8-C8 -> 0.24 | AA8: =Z8-Z7 -> 0.011666667 | AB8: 13.72 | AC8: -5.7044674 | AD8: =M8-N8 -> 0.047927098
A9: 41640 | B9: 0.085721878 | C9: -0.13666667 | D9: 0.0875 | E9: 0.23583333 | F9: 0.29583333 | G9: =0.3657*E9+(1-0.3657)*D9 -> 0.1417455 | H9: 2.2263747 | I9: 0.52818166 | J9: 1822.36 | K9: =-1+J9/J8 -> 0.0080651407 | L9: =L8*2/3+L11/3 -> 100.41667 | M9: =L9/J9 -> 0.055102541 | N9: 0.0058333333 | O9: -0.84486748 | P9: =F9-D9 -> 0.20833333 | Q9: =2*E9-F9-D9 -> 0.088333333 | R9: 0.035725 | S9: =R9-N9 -> 0.029891667 | T9: =D9-B9 -> 0.0017781225 | U9: =P9-P8 -> -0.0041666667 | V9: =Q9-Q8 -> -0.029166667 | W9: =H9-G9 -> 2.0846292 | X9: =I9-H9 -> -1.698193 | Y9: =K9-I9 -> -0.52011652 | Z9: =D9-C9 -> 0.22416667 | AA9: =Z9-Z8 -> -0.015833333 | AB9: 18.41 | AC9: 33.793605 | AD9: =M9-N9 -> 0.049269208
A10: 41671 | B10: 0.089329439 | C10: -0.14416667 | D10: 0.089166667 | E10: 0.23833333 | F10: 0.29583333 | G10: =0.3657*E10+(1-0.3657)*D10 -> 0.14371692 | H10: 0.33187521 | I10: 1.9235566 | J10: 1817.04 | K10: =-1+J10/J9 -> -0.0029192915 | L10: =L8/3+L11*2/3 -> 100.63333 | M10: =L10/J10 -> 0.055383114 | N10: 0.0058333333 | O10: 2.1320616 | P10: =F10-D10 -> 0.20666667 | Q10: =2*E10-F10-D10 -> 0.091666667 | R10: 0.034975 | S10: =R10-N10 -> 0.029141667 | T10: =D10-B10 -> -0.00016277218 | U10: =P10-P9 -> -0.0016666667 | V10: =Q10-Q9 -> 0.0033333333 | W10: =H10-G10 -> 0.18815829 | X10: =I10-H10 -> 1.5916814 | Y10: =K10-I10 -> -1.9264759 | Z10: =D10-C10 -> 0.23333333 | AA10: =Z10-Z9 -> 0.0091666667 | AB10: 14 | AC10: -23.954373 | AD10: =M10-N10 -> 0.049549781
A11: 41699 | B11: 0.098214001 | C11: -0.13833333 | D11: 0.099166667 | E11: 0.23916667 | F11: 0.29583333 | G11: =0.3657*E11+(1-0.3657)*D11 -> 0.15036467 | H11: -0.15367518 | I11: 0.018661357 | J11: 1863.52 | K11: =-1+J11/J10 -> 0.025580064 | L11: 100.85 | M11: =L11/J11 -> 0.054118013 | N11: 0.0066666667 | O11: -0.4241401 | P11: =F11-D11 -> 0.19666667 | Q11: =2*E11-F11-D11 -> 0.083333333 | R11: 0.034658333 | S11: =R11-N11 -> 0.027991667 | T11: =D11-B11 -> 0.00095266584 | U11: =P11-P10 -> -0.01 | V11: =Q11-Q10 -> -0.0083333333 | W11: =H11-G11 -> -0.30403985 | X11: =I11-H11 -> 0.17233654 | Y11: =K11-I11 -> 0.0069187077 | Z11: =D11-C11 -> 0.2375 | AA11: =Z11-Z10 -> 0.0041666667 | AB11: 13.88 | AC11: -1.5602837 | AD11: =M11-N11 -> 0.047451347
A12: 41730 | B12: 0.10053544 | C12: -0.145 | D12: 0.1 | E12: 0.23416667 | F12: 0.29166667 | G12: =0.3657*E12+(1-0.3657)*D12 -> 0.14906475 | H12: 1.3714712 | I12: 0.65116083 | J12: 1864.26 | K12: =-1+J12/J11 -> 0.00039709797 | L12: =L11*2/3+L14/3 -> 101.60667 | M12: =L12/J12 -> 0.054502412 | N12: 0.0075 | O12: 0.74520035 | P12: =F12-D12 -> 0.19166667 | Q12: =2*E12-F12-D12 -> 0.076666667 | R12: 0.035166667 | S12: =R12-N12 -> 0.027666667 | T12: =D12-B12 -> -0.00053543916 | U12: =P12-P11 -> -0.005 | V12: =Q12-Q11 -> -0.0066666667 | W12: =H12-G12 -> 1.2224064 | X12: =I12-H12 -> -0.72031035 | Y12: =K12-I12 -> -0.65076373 | Z12: =D12-C12 -> 0.245 | AA12: =Z12-Z11 -> 0.0075 | AB12: 13.41 | AC12: 2.4446142 | AD12: =M12-N12 -> 0.047002412
A13: 41760 | B13: 0.10034889 | C13: -0.135 | D13: 0.098333333 | E13: 0.225 | F13: 0.28416667 | G13: =0.3657*E13+(1-0.3657)*D13 -> 0.14465533 | H13: 1.263466 | I13: 0.52857926 | J13: 1889.77 | K13: =-1+J13/J12 -> 0.013683714 | L13: =L11/3+L14*2/3 -> 102.36333 | M13: =L13/J13 -> 0.054167086 | N13: 0.0075 | O13: 1.3893836 | P13: =F13-D13 -> 0.18583333 | Q13: =2*E13-F13-D13 -> 0.0675 | R13: 0.035275 | S13: =R13-N13 -> 0.027775 | T13: =D13-B13 -> -0.0020155552 | U13: =P13-P12 -> -0.0058333333 | V13: =Q13-Q12 -> -0.0091666667 | W13: =H13-G13 -> 1.1188107 | X13: =I13-H13 -> -0.73488673 | Y13: =K13-I13 -> -0.51489555 | Z13: =D13-C13 -> 0.23333333 | AA13: =Z13-Z12 -> -0.011666667 | AB13: 11.4 | AC13: -11.696359 | AD13: =M13-N13 -> 0.046667086
A14: 41791 | B14: 0.12043899 | C14: -0.115 | D14: 0.11833333 | E14: 0.23416667 | F14: 0.2875 | G14: =0.3657*E14+(1-0.3657)*D14 -> 0.16069358 | H14: -0.2331738 | I14: 0.87980609 | J14: 1947.09 | K14: =-1+J14/J13 -> 0.030331733 | L14: 103.12 | M14: =L14/J14 -> 0.052961086 | N14: 0.0083333333 | O14: -0.15960421 | P14: =F14-D14 -> 0.16916667 | Q14: =2*E14-F14-D14 -> 0.0625 | R14: 0.035425 | S14: =R14-N14 -> 0.027091667 | T14: =D14-B14 -> -0.0021056525 | U14: =P14-P13 -> -0.016666667 | V14: =Q14-Q13 -> -0.005 | W14: =H14-G14 -> -0.39386739 | X14: =I14-H14 -> 1.1129799 | Y14: =K14-I14 -> -0.84947435 | Z14: =D14-C14 -> 0.23333333 | AA14: =Z14-Z13 -> 0 | AB14: 11.57 | AC14: -2.5273799 | AD14: =M14-N14 -> 0.044627752
A15: 41821 | B15: 0.12138223 | C15: -0.11333333 | D15: 0.11916667 | E15: 0.23 | F15: 0.27666667 | G15: =0.3657*E15+(1-0.3657)*D15 -> 0.15969842 | H15: 0.39169156 | I15: -1.3143737 | J15: 1973.1 | K15: =-1+J15/J14 -> 0.013358396 | L15: =L14*2/3+L17/3 -> 104.06667 | M15: =L15/J15 -> 0.052742723 | N15: 0.0075 | O15: 0.0021744398 | P15: =F15-D15 -> 0.1575 | Q15: =2*E15-F15-D15 -> 0.064166667 | R15: 0.035691667 | S15: =R15-N15 -> 0.028191667 | T15: =D15-B15 -> -0.0022155666 | U15: =P15-P14 -> -0.011666667 | V15: =Q15-Q14 -> 0.0016666667 | W15: =H15-G15 -> 0.23199315 | X15: =I15-H15 -> -1.7060652 | Y15: =K15-I15 -> 1.3277321 | Z15: =D15-C15 -> 0.2325 | AA15: =Z15-Z14 -> -0.00083333333 | AB15: 16.95 | AC15: 64.244186 | AD15: =M15-N15 -> 0.045242723
A16: 41852 | B16: 0.10415775 | C16: -0.135 | D16: 0.10166667 | E16: 0.19916667 | F16: 0.2475 | G16: =0.3657*E16+(1-0.3657)*D16 -> 0.13732242 | H16: 3.1883543 | I16: 1.3564338 | J16: 1961.53 | K16: =-1+J16/J15 -> -0.005863869 | L16: =L14/3+L17*2/3 -> 105.01333 | M16: =L16/J16 -> 0.05353644 | N16: 0.0075 | O16: 2.1528111 | P16: =F16-D16 -> 0.14583333 | Q16: =2*E16-F16-D16 -> 0.049166667 | R16: 0.035233333 | S16: =R16-N16 -> 0.027733333 | T16: =D16-B16 -> -0.0024910871 | U16: =P16-P15 -> -0.011666667 | V16: =Q16-Q15 -> -0.015 | W16: =H16-G16 -> 3.0510319 | X16: =I16-H16 -> -1.8319205 | Y16: =K16-I16 -> -1.3622977 | Z16: =D16-C16 -> 0.23666667 | AA16: =Z16-Z15 -> 0.0041666667 | AB16: 11.98 | AC16: -20.767196 | AD16: =M16-N16 -> 0.04603644
A17: 41883 | B17: 0.10844735 | C17: -0.11666667 | D17: 0.10583333 | E17: 0.20583333 | F17: 0.255 | G17: =0.3657*E17+(1-0.3657)*D17 -> 0.14240333 | H17: -0.43329142 | I17: -1.7029454 | J17: 1993.23 | K17: =-1+J17/J16 -> 0.016160854 | L17: 105.96 | M17: =L17/J17 -> 0.053159946 | N17: 0.0075 | O17: -0.63321922 | P17: =F17-D17 -> 0.14916667 | Q17: =2*E17-F17-D17 -> 0.050833333 | R17: 0.035991667 | S17: =R17-N17 -> 0.028491667 | T17: =D17-B17 -> -0.0026140146 | U17: =P17-P16 -> 0.0033333333 | V17: =Q17-Q16 -> 0.0016666667 | W17: =H17-G17 -> -0.57569476 | X17: =I17-H17 -> -1.269654 | Y17: =K17-I17 -> 1.7191063 | Z17: =D17-C17 -> 0.2225 | AA17: =Z17-Z16 -> -0.014166667 | AB17: 16.31 | AC17: 31.957929 | AD17: =M17-N17 -> 0.045659946
A18: 41913 | B18: 0.091060826 | C18: -0.11583333 | D18: 0.088333333 | E18: 0.1925 | F18: 0.24833333 | G18: =0.3657*E18+(1-0.3657)*D18 -> 0.12642708 | H18: 0.47151302 | I18: 1.6125622 | J18: 1937.27 | K18: =-1+J18/J17 -> -0.028075034 | L18: =L17*2/3+L20/3 -> 104.74333 | M18: =L18/J18 -> 0.054067494 | N18: 0.0075 | O18: 0.5431128 | P18: =F18-D18 -> 0.16 | Q18: =2*E18-F18-D18 -> 0.048333333 | R18: 0.0359 | S18: =R18-N18 -> 0.0284 | T18: =D18-B18 -> -0.0027274931 | U18: =P18-P17 -> 0.010833333 | V18: =Q18-Q17 -> -0.0025 | W18: =H18-G18 -> 0.34508593 | X18: =I18-H18 -> 1.1410492 | Y18: =K18-I18 -> -1.6406373 | Z18: =D18-C18 -> 0.20416667 | AA18: =Z18-Z17 -> -0.018333333 | AB18: 14.03 | AC18: -9.2496766 | AD18: =M18-N18 -> 0.046567494
A19: 41944 | B19: 0.072590193 | C19: -0.1275 | D19: 0.070833333 | E19: 0.16583333 | F19: 0.22166667 | G19: =0.3657*E19+(1-0.3657)*D19 -> 0.10557483 | H19: 2.5724386 | I19: -0.45060331 | J19: 2044.57 | K19: =-1+J19/J18 -> 0.05538722 | L19: =L17/3+L20*2/3 -> 103.52667 | M19: =L19/J19 -> 0.050634934 | N19: 0.0075 | O19: 2.6535892 | P19: =F19-D19 -> 0.15083333 | Q19: =2*E19-F19-D19 -> 0.039166667 | R19: 0.036041667 | S19: =R19-N19 -> 0.028541667 | T19: =D19-B19 -> -0.00175686 | U19: =P19-P18 -> -0.0091666667 | V19: =Q19-Q18 -> -0.0091666667 | W19: =H19-G19 -> 2.4668638 | X19: =I19-H19 -> -3.0230419 | Y19: =K19-I19 -> 0.50599053 | Z19: =D19-C19 -> 0.19833333 | AA19: =Z19-Z18 -> -0.0058333333 | AB19: 13.33 | AC19: -4.9893086 | AD19: =M19-N19 -> 0.043134934
A20: 41974 | B20: 0.071621437 | C20: -0.13583333 | D20: 0.064166667 | E20: 0.15166667 | F20: 0.20666667 | G20: =0.3657*E20+(1-0.3657)*D20 -> 0.096165417 | H20: 1.4790637 | I20: -1.2777746 | J20: 2054.27 | K20: =-1+J20/J19 -> 0.0047442739 | L20: 102.31 | M20: =L20/J20 -> 0.04980358 | N20: 0.01 | O20: -0.1865194 | P20: =F20-D20 -> 0.1425 | Q20: =2*E20-F20-D20 -> 0.0325 | R20: 0.035666667 | S20: =R20-N20 -> 0.025666667 | T20: =D20-B20 -> -0.0074547702 | U20: =P20-P19 -> -0.0083333333 | V20: =Q20-Q19 -> -0.0066666667 | W20: =H20-G20 -> 1.3828983 | X20: =I20-H20 -> -2.7568383 | Y20: =K20-I20 -> 1.2825189 | Z20: =D20-C20 -> 0.2 | AA20: =Z20-Z19 -> 0.0016666667 | AB20: 19.2 | AC20: 53.969527 | AD20: =M20-N20 -> 0.03980358
A21: 42005 | B21: 0.057046471 | C21: -0.12 | D21: 0.05 | E21: 0.11583333 | F21: 0.1675 | G21: =0.3657*E21+(1-0.3657)*D21 -> 0.07407525 | H21: 6.0089659 | I21: 1.1830048 | J21: 2028.18 | K21: =-1+J21/J20 -> -0.012700375 | L21: =L20*2/3+L23/3 -> 101.29 | M21: =L21/J21 -> 0.049941327 | N21: 0.0091666667 | O21: 2.4047018 | P21: =F21-D21 -> 0.1175 | Q21: =2*E21-F21-D21 -> 0.014166667 | R21: 0.036291667 | S21: =R21-N21 -> 0.027125 | T21: =D21-B21 -> -0.0070464705 | U21: =P21-P20 -> -0.025 | V21: =Q21-Q20 -> -0.018333333 | W21: =H21-G21 -> 5.9348907 | X21: =I21-H21 -> -4.8259611 | Y21: =K21-I21 -> -1.1957052 | Z21: =D21-C21 -> 0.17 | AA21: =Z21-Z20 -> -0.03 | AB21: 20.97 | AC21: 17.875211 | AD21: =M21-N21 -> 0.04077466
A22: 42036 | B22: 0.079048727 | C22: -0.11583333 | D22: 0.071666667 | E22: 0.155 | F22: 0.205 | G22: =0.3657*E22+(1-0.3657)*D22 -> 0.10214167 | H22: -3.6375516 | I22: 2.0940891 | J22: 2082.2 | K22: =-1+J22/J21 -> 0.026634717 | L22: =L20/3+L23*2/3 -> 100.27 | M22: =L22/J22 -> 0.048155797 | N22: 0.0091666667 | O22: 0.82206753 | P22: =F22-D22 -> 0.13333333 | Q22: =2*E22-F22-D22 -> 0.033333333 | R22: 0.037591667 | S22: =R22-N22 -> 0.028425 | T22: =D22-B22 -> -0.0073820605 | U22: =P22-P21 -> 0.015833333 | V22: =Q22-Q21 -> 0.019166667 | W22: =H22-G22 -> -3.7396932 | X22: =I22-H22 -> 5.7316407 | Y22: =K22-I22 -> -2.0674544 | Z22: =D22-C22 -> 0.1875 | AA22: =Z22-Z21 -> 0.0175 | AB22: 13.34 | AC22: -36.385312 | AD22: =M22-N22 -> 0.03898913
A23: 42064 | B23: 0.064717583 | C23: -0.14416667 | D23: 0.055833333 | E23: 0.13833333 | F23: 0.19083333 | G23: =0.3657*E23+(1-0.3657)*D23 -> 0.086003583 | H23: 1.1854893 | I23: -0.77587498 | J23: 2079.99 | K23: =-1+J23/J22 -> -0.0010613774 | L23: 99.25 | M23: =L23/J23 -> 0.047716576 | N23: 0.0091666667 | O23: 0.79790761 | P23: =F23-D23 -> 0.135 | Q23: =2*E23-F23-D23 -> 0.03 | R23: 0.038066667 | S23: =R23-N23 -> 0.0289 | T23: =D23-B23 -> -0.0088842496 | U23: =P23-P22 -> 0.0016666667 | V23: =Q23-Q22 -> -0.0033333333 | W23: =H23-G23 -> 1.0994857 | X23: =I23-H23 -> -1.9613643 | Y23: =K23-I23 -> 0.7748136 | Z23: =D23-C23 -> 0.2 | AA23: =Z23-Z22 -> 0.0125 | AB23: 15.29 | AC23: 7.4490513 | AD23: =M23-N23 -> 0.038549909
A24: 42095 | B24: 0.075883935 | C24: -0.14666667 | D24: 0.07 | E24: 0.16166667 | F24: 0.21083333 | G24: =0.3657*E24+(1-0.3657)*D24 -> 0.1035225 | H24: -2.2229609 | I24: 0.65171916 | J24: 2094.86 | K24: =-1+J24/J23 -> 0.0071490728 | L24: =L23*2/3+L26/3 -> 97.803333 | M24: =L24/J24 -> 0.046687289 | N24: 0.01 | O24: -0.23417506 | P24: =F24-D24 -> 0.14083333 | Q24: =2*E24-F24-D24 -> 0.0425 | R24: 0.038116667 | S24: =R24-N24 -> 0.028116667 | T24: =D24-B24 -> -0.0058839348 | U24: =P24-P23 -> 0.0058333333 | V24: =Q24-Q23 -> 0.0125 | W24: =H24-G24 -> -2.3264834 | X24: =I24-H24 -> 2.8746801 | Y24: =K24-I24 -> -0.64457008 | Z24: =D24-C24 -> 0.21666667 | AA24: =Z24-Z23 -> 0.016666667 | AB24: 14.55 | AC24: -0.81799591 | AD24: =M24-N24 -> 0.036687289
A25: 42125 | B25: 0.073903398 | C25: -0.14083333 | D25: 0.0675 | E25: 0.16 | F25: 0.21083333 | G25: =0.3657*E25+(1-0.3657)*D25 -> 0.10132725 | H25: 0.37532703 | I25: -0.13018686 | J25: 2111.94 | K25: =-1+J25/J24 -> 0.0081532895 | L25: =L23/3+L26*2/3 -> 96.356667 | M25: =L25/J25 -> 0.045624718 | N25: 0.01 | O25: 0.4490633 | P25: =F25-D25 -> 0.14333333 | Q25: =2*E25-F25-D25 -> 0.041666667 | R25: 0.0385 | S25: =R25-N25 -> 0.0285 | T25: =D25-B25 -> -0.0064033976 | U25: =P25-P24 -> 0.0025 | V25: =Q25-Q24 -> -0.00083333333 | W25: =H25-G25 -> 0.27399978 | X25: =I25-H25 -> -0.5055139 | Y25: =K25-I25 -> 0.13834015 | Z25: =D25-C25 -> 0.20833333 | AA25: =Z25-Z24 -> -0.0083333333 | AB25: 13.84 | AC25: 8.976378 | AD25: =M25-N25 -> 0.035624718
A26: 42156 | B26: 0.086698665 | C26: -0.135 | D26: 0.08 | E26: 0.18 | F26: 0.22916667 | G26: =0.3657*E26+(1-0.3657)*D26 -> 0.11657 | H26: -3.6542343 | I26: -1.8355748 | J26: 2099.29 | K26: =-1+J26/J25 -> -0.0059897535 | L26: 94.91 | M26: =L26/J26 -> 0.045210524 | N26: 0.010833333 | O26: -3.3442886 | P26: =F26-D26 -> 0.14916667 | Q26: =2*E26-F26-D26 -> 0.050833333 | R26: 0.03805 | S26: =R26-N26 -> 0.027216667 | T26: =D26-B26 -> -0.0066986653 | U26: =P26-P25 -> 0.0058333333 | V26: =Q26-Q25 -> 0.0091666667 | W26: =H26-G26 -> -3.7708043 | X26: =I26-H26 -> 1.8186596 | Y26: =K26-I26 -> 1.829585 | Z26: =D26-C26 -> 0.215 | AA26: =Z26-Z25 -> 0.0066666667 | AB26: 18.23 | AC26: 33.455344 | AD26: =M26-N26 -> 0.03437719
A27: 42186 | B27: 0.087778972 | C27: -0.11833333 | D27: 0.079166667 | E27: 0.1675 | F27: 0.21583333 | G27: =0.3657*E27+(1-0.3657)*D27 -> 0.11147017 | H27: 2.5427263 | I27: 0.19396134 | J27: 2094.14 | K27: =-1+J27/J26 -> -0.0024532104 | L27: =L26*2/3+L29/3 -> 93.493333 | M27: =L27/J27 -> 0.044645216 | N27: 0.010833333 | O27: 1.9551601 | P27: =F27-D27 -> 0.13666667 | Q27: =2*E27-F27-D27 -> 0.04 | R27: 0.037908333 | S27: =R27-N27 -> 0.027075 | T27: =D27-B27 -> -0.0086123056 | U27: =P27-P26 -> -0.0125 | V27: =Q27-Q26 -> -0.010833333 | W27: =H27-G27 -> 2.4312561 | X27: =I27-H27 -> -2.3487649 | Y27: =K27-I27 -> -0.19641455 | Z27: =D27-C27 -> 0.1975 | AA27: =Z27-Z26 -> -0.0175 | AB27: 12.12 | AC27: -28.747795 | AD27: =M27-N27 -> 0.033811883
A28: 42217 | B28: 0.080176109 | C28: -0.10416667 | D28: 0.075 | E28: 0.16416667 | F28: 0.21666667 | G28: =0.3657*E28+(1-0.3657)*D28 -> 0.10760825 | H28: -2.0562685 | I28: -1.5737927 | J28: 2039.87 | K28: =-1+J28/J27 -> -0.025915173 | L28: =L26/3+L29*2/3 -> 92.076667 | M28: =L28/J28 -> 0.045138497 | N28: 0.011666667 | O28: -2.9682787 | P28: =F28-D28 -> 0.14166667 | Q28: =2*E28-F28-D28 -> 0.036666667 | R28: 0.03825 | S28: =R28-N28 -> 0.026583333 | T28: =D28-B28 -> -0.005176109 | U28: =P28-P27 -> 0.005 | V28: =Q28-Q27 -> -0.0033333333 | W28: =H28-G28 -> -2.1638767 | X28: =I28-H28 -> 0.48247579 | Y28: =K28-I28 -> 1.5478775 | Z28: =D28-C28 -> 0.17916667 | AA28: =Z28-Z27 -> -0.018333333 | AB28: 28.43 | AC28: 118.69231 | AD28: =M28-N28 -> 0.033471831
A29: 42248 | B29: 0.067917662 | C29: -0.12166667 | D29: 0.064166667 | E29: 0.14916667 | F29: 0.20916667 | G29: =0.3657*E29+(1-0.3657)*D29 -> 0.095251167 | H29: 0.59783704 | I29: -2.8866131 | J29: 1944.41 | K29: =-1+J29/J28 -> -0.0467971 | L29: 90.66 | M29: =L29/J29 -> 0.046625969 | N29: 0.011666667 | O29: -0.94912629 | P29: =F29-D29 -> 0.145 | Q29: =2*E29-F29-D29 -> 0.025 | R29: 0.037866667 | S29: =R29-N29 -> 0.0262 | T29: =D29-B29 -> -0.0037509955 | U29: =P29-P28 -> 0.0033333333 | V29: =Q29-Q28 -> -0.011666667 | W29: =H29-G29 -> 0.50258588 | X29: =I29-H29 -> -3.4844501 | Y29: =K29-I29 -> 2.839816 | Z29: =D29-C29 -> 0.18583333 | AA29: =Z29-Z28 -> 0.0066666667 | AB29: 24.5 | AC29: -6.094289 | AD29: =M29-N29 -> 0.034959302
A30: 42278 | B30: 0.072056751 | C30: -0.11583333 | D30: 0.070833333 | E30: 0.1625 | F30: 0.22083333 | G30: =0.3657*E30+(1-0.3657)*D30 -> 0.10435583 | H30: 0.11936853 | I30: 3.485803 | J30: 2024.81 | K30: =-1+J30/J29 -> 0.041349304 | L30: =L29*2/3+L32/3 -> 89.283333 | M30: =L30/J30 -> 0.044094672 | N30: 0.01 | O30: 2.6833913 | P30: =F30-D30 -> 0.15 | Q30: =2*E30-F30-D30 -> 0.033333333 | R30: 0.038516667 | S30: =R30-N30 -> 0.028516667 | T30: =D30-B30 -> -0.0012234181 | U30: =P30-P29 -> 0.005 | V30: =Q30-Q29 -> 0.0083333333 | W30: =H30-G30 -> 0.015012702 | X30: =I30-H30 -> 3.3664345 | Y30: =K30-I30 -> -3.4444537 | Z30: =D30-C30 -> 0.18666667 | AA30: =Z30-Z29 -> 0.00083333333 | AB30: 15.07 | AC30: -22.876151 | AD30: =M30-N30 -> 0.034094672
A31: 42309 | B31: 0.067605646 | C31: -0.12166667 | D31: 0.069166667 | E31: 0.15583333 | F31: 0.21583333 | G31: =0.3657*E31+(1-0.3657)*D31 -> 0.10086067 | H31: 2.1742913 | I31: -1.8790029 | J31: 2080.62 | K31: =-1+J31/J30 -> 0.02756308 | L31: =L29/3+L32*2/3 -> 87.906667 | M31: =L31/J31 -> 0.042250227 | N31: 0.01 | O31: 1.0849102 | P31: =F31-D31 -> 0.14666667 | Q31: =2*E31-F31-D31 -> 0.026666667 | R31: 0.038633333 | S31: =R31-N31 -> 0.028633333 | T31: =D31-B31 -> 0.0015610207 | U31: =P31-P30 -> -0.0033333333 | V31: =Q31-Q30 -> -0.0066666667 | W31: =H31-G31 -> 2.0734307 | X31: =I31-H31 -> -4.0532943 | Y31: =K31-I31 -> 1.906566 | Z31: =D31-C31 -> 0.19083333 | AA31: =Z31-Z30 -> 0.0041666667 | AB31: 16.13 | AC31: 13.992933 | AD31: =M31-N31 -> 0.032250227
A32: 42339 | B32: 0.0824033 | C32: -0.1 | D32: 0.079166667 | E32: 0.1675 | F32: 0.22583333 | G32: =0.3657*E32+(1-0.3657)*D32 -> 0.11147017 | H32: -1.3050321 | I32: -2.2541702 | J32: 2054.08 | K32: =-1+J32/J31 -> -0.012755813 | L32: 86.53 | M32: =L32/J32 -> 0.042125915 | N32: 0.02 | O32: -0.60205936 | P32: =F32-D32 -> 0.14666667 | Q32: =2*E32-F32-D32 -> 0.03 | R32: 0.038125 | S32: =R32-N32 -> 0.018125 | T32: =D32-B32 -> -0.0032366331 | U32: =P32-P31 -> 0 | V32: =Q32-Q31 -> 0.0033333333 | W32: =H32-G32 -> -1.4165022 | X32: =I32-H32 -> -0.94913814 | Y32: =K32-I32 -> 2.2414144 | Z32: =D32-C32 -> 0.17916667 | AA32: =Z32-Z31 -> -0.011666667 | AB32: 18.21 | AC32: 0.55218112 | AD32: =M32-N32 -> 0.022125915
A33: 42370 | B33: 0.047280347 | C33: -0.13083333 | D33: 0.046666667 | E33: 0.13666667 | F33: 0.19916667 | G33: =0.3657*E33+(1-0.3657)*D33 -> 0.079579667 | H33: 0.74773687 | I33: -1.6993921 | J33: 1918.6 | K33: =-1+J33/J32 -> -0.065956535 | L33: =L32*2/3+L35/3 -> 86.5 | M33: =L33/J33 -> 0.045084958 | N33: 0.028333333 | O33: -1.3845335 | P33: =F33-D33 -> 0.1525 | Q33: =2*E33-F33-D33 -> 0.0275 | R33: 0.038825 | S33: =R33-N33 -> 0.010491667 | T33: =D33-B33 -> -0.00061367997 | U33: =P33-P32 -> 0.0058333333 | V33: =Q33-Q32 -> -0.0025 | W33: =H33-G33 -> 0.66815721 | X33: =I33-H33 -> -2.447129 | Y33: =K33-I33 -> 1.6334355 | Z33: =D33-C33 -> 0.1775 | AA33: =Z33-Z32 -> -0.0016666667 | AB33: 20.2 | AC33: 10.928062 | AD33: =M33-N33 -> 0.016751624
A34: 42401 | B34: 0.02952729 | C34: -0.12083333 | D34: 0.031666667 | E34: 0.1175 | F34: 0.1925 | G34: =0.3657*E34+(1-0.3657)*D34 -> 0.063055917 | H34: -0.74469809 | I34: 0.79501459 | J34: 1904.42 | K34: =-1+J34/J33 -> -0.0073908058 | L34: =L32/3+L35*2/3 -> 86.47 | M34: =L34/J34 -> 0.0454049 | N34: 0.031666667 | O34: 0.51269215 | P34: =F34-D34 -> 0.16083333 | Q34: =2*E34-F34-D34 -> 0.010833333 | R34: 0.038808333 | S34: =R34-N34 -> 0.0071416667 | T34: =D34-B34 -> 0.0021393763 | U34: =P34-P33 -> 0.0083333333 | V34: =Q34-Q33 -> -0.016666667 | W34: =H34-G34 -> -0.80775401 | X34: =I34-H34 -> 1.5397127 | Y34: =K34-I34 -> -0.80240539 | Z34: =D34-C34 -> 0.1525 | AA34: =Z34-Z33 -> -0.025 | AB34: 20.55 | AC34: 2.8528529 | AD34: =M34-N34 -> 0.013738234
A35: 42430 | B35: 0.039134295 | C35: -0.15083333 | D35: 0.04 | E35: 0.125 | F35: 0.19333333 | G35: =0.3657*E35+(1-0.3657)*D35 -> 0.0710845 | H35: 3.6665013 | I35: 3.688794 | J35: 2021.95 | K35: =-1+J35/J34 -> 0.061714328 | L35: 86.44 | M35: =L35/J35 -> 0.04275081 | N35: 0.03 | O35: 2.1127325 | P35: =F35-D35 -> 0.15333333 | Q35: =2*E35-F35-D35 -> 0.016666667 | R35: 0.038716667 | S35: =R35-N35 -> 0.0087166667 | T35: =D35-B35 -> 0.00086570504 | U35: =P35-P34 -> -0.0075 | V35: =Q35-Q34 -> 0.0058333333 | W35: =H35-G35 -> 3.5954168 | X35: =I35-H35 -> 0.022292749 | Y35: =K35-I35 -> -3.6270797 | Z35: =D35-C35 -> 0.19083333 | AA35: =Z35-Z34 -> 0.038333333 | AB35: 13.95 | AC35: -16.467066 | AD35: =M35-N35 -> 0.01275081
A36: 42461 | B36: 0.049262317 | C36: -0.14583333 | D36: 0.050833333 | E36: 0.14083333 | F36: 0.20416667 | G36: =0.3657*E36+(1-0.3657)*D36 -> 0.083746333 | H36: 0.99565048 | I36: 2.3541004 | J36: 2075.54 | K36: =-1+J36/J35 -> 0.026504117 | L36: =L35*2/3+L38/3 -> 86.6 | M36: =L36/J36 -> 0.041724081 | N36: 0.030833333 | O36: 0.4466425 | P36: =F36-D36 -> 0.15333333 | Q36: =2*E36-F36-D36 -> 0.026666667 | R36: 0.038858333 | S36: =R36-N36 -> 0.008025 | T36: =D36-B36 -> 0.0015710166 | U36: =P36-P35 -> 0 | V36: =Q36-Q35 -> 0.01 | W36: =H36-G36 -> 0.91190414 | X36: =I36-H36 -> 1.3584499 | Y36: =K36-I36 -> -2.3275963 | Z36: =D36-C36 -> 0.19666667 | AA36: =Z36-Z35 -> 0.0058333333 | AB36: 15.7 | AC36: 11.189802 | AD36: =M36-N36 -> 0.010890748
A37: 42491 | B37: 0.048811821 | C37: -0.14166667 | D37: 0.046666667 | E37: 0.12916667 | F37: 0.19 | G37: =0.3657*E37+(1-0.3657)*D37 -> 0.076836917 | H37: 0.931525 | I37: 0.32928549 | J37: 2065.55 | K37: =-1+J37/J36 -> -0.0048132052 | L37: =L35/3+L38*2/3 -> 86.76 | M37: =L37/J37 -> 0.042003341 | N37: 0.030833333 | O37: 0.80909571 | P37: =F37-D37 -> 0.14333333 | Q37: =2*E37-F37-D37 -> 0.021666667 | R37: 0.038608333 | S37: =R37-N37 -> 0.007775 | T37: =D37-B37 -> -0.0021451548 | U37: =P37-P36 -> -0.01 | V37: =Q37-Q36 -> -0.005 | W37: =H37-G37 -> 0.85468808 | X37: =I37-H37 -> -0.60223951 | Y37: =K37-I37 -> -0.33409869 | Z37: =D37-C37 -> 0.18833333 | AA37: =Z37-Z36 -> -0.0083333333 | AB37: 14.19 | AC37: -9.0384615 | AD37: =M37-N37 -> 0.011170007
A38: 42522 | B38: 0.0089930273 | C38: -0.19333333 | D38: 0.0125 | E38: 0.085833333 | F38: 0.14916667 | G38: =0.3657*E38+(1-0.3657)*D38 -> 0.039318 | H38: 3.605795 | I38: 0.76956632 | J38: 2083.89 | K38: =-1+J38/J37 -> 0.0088789911 | L38: 86.92 | M38: =L38/J38 -> 0.041710455 | N38: 0.031666667 | O38: 3.3950819 | P38: =F38-D38 -> 0.13666667 | Q38: =2*E38-F38-D38 -> 0.01 | R38: 0.038316667 | S38: =R38-N38 -> 0.00665 | T38: =D38-B38 -> 0.0035069727 | U38: =P38-P37 -> -0.0066666667 | V38: =Q38-Q37 -> -0.011666667 | W38: =H38-G38 -> 3.566477 | X38: =I38-H38 -> -2.8362287 | Y38: =K38-I38 -> -0.76068732 | Z38: =D38-C38 -> 0.20583333 | AA38: =Z38-Z37 -> 0.0175 | AB38: 15.63 | AC38: 16.035635 | AD38: =M38-N38 -> 0.010043788
A39: 42552 | B39: 0.010781126 | C39: -0.21 | D39: 0.0075 | E39: 0.066666667 | F39: 0.13083333 | G39: =0.3657*E39+(1-0.3657)*D39 -> 0.02913725 | H39: 5.0756542 | I39: 2.3978115 | J39: 2148.9 | K39: =-1+J39/J38 -> 0.031196464 | L39: =L38*2/3+L41/3 -> 87.643333 | M39: =L39/J39 -> 0.040785208 | N39: 0.0325 | O39: 3.1095109 | P39: =F39-D39 -> 0.12333333 | Q39: =2*E39-F39-D39 -> -0.005 | R39: 0.038141667 | S39: =R39-N39 -> 0.0056416667 | T39: =D39-B39 -> -0.0032811258 | U39: =P39-P38 -> -0.013333333 | V39: =Q39-Q38 -> -0.015 | W39: =H39-G39 -> 5.046517 | X39: =I39-H39 -> -2.6778428 | Y39: =K39-I39 -> -2.366615 | Z39: =D39-C39 -> 0.2175 | AA39: =Z39-Z38 -> 0.011666667 | AB39: 11.87 | AC39: -19.634394 | AD39: =M39-N39 -> 0.0082852079
A40: 42583 | B40: 0.0090552495 | C40: -0.22583333 | D40: 0.0083333333 | E40: 0.055 | F40: 0.10666667 | G40: =0.3657*E40+(1-0.3657)*D40 -> 0.025399333 | H40: 3.4464466 | I40: 2.0430672 | J40: 2170.95 | K40: =-1+J40/J39 -> 0.010261064 | L40: =L38/3+L41*2/3 -> 88.366667 | M40: =L40/J40 -> 0.040704146 | N40: 0.033333333 | O40: 1.5752476 | P40: =F40-D40 -> 0.098333333 | Q40: =2*E40-F40-D40 -> -0.005 | R40: 0.02065 | S40: =R40-N40 -> -0.012683333 | T40: =D40-B40 -> -0.00072191616 | U40: =P40-P39 -> -0.025 | V40: =Q40-Q39 -> -8.6736174e-18 | W40: =H40-G40 -> 3.4210473 | X40: =I40-H40 -> -1.4033794 | Y40: =K40-I40 -> -2.0328062 | Z40: =D40-C40 -> 0.23416667 | AA40: =Z40-Z39 -> 0.016666667 | AB40: 13.42 | AC40: 8.0515298 | AD40: =M40-N40 -> 0.0073708131
A41: 42614 | B41: 0.0099645638 | C41: -0.21916667 | D41: 0.0083333333 | E41: 0.066666667 | F41: 0.12666667 | G41: =0.3657*E41+(1-0.3657)*D41 -> 0.029665833 | H41: -1.8753548 | I41: -0.0056051193 | J41: 2157.69 | K41: =-1+J41/J40 -> -0.0061079251 | L41: 89.09 | M41: =L41/J41 -> 0.041289527 | N41: 0.033333333 | O41: 0.39414405 | P41: =F41-D41 -> 0.11833333 | Q41: =2*E41-F41-D41 -> -0.0016666667 | R41: 0.01775 | S41: =R41-N41 -> -0.015583333 | T41: =D41-B41 -> -0.0016312304 | U41: =P41-P40 -> 0.02 | V41: =Q41-Q40 -> 0.0033333333 | W41: =H41-G41 -> -1.9050206 | X41: =I41-H41 -> 1.8697497 | Y41: =K41-I41 -> -0.00050280584 | Z41: =D41-C41 -> 0.2275 | AA41: =Z41-Z40 -> -0.0066666667 | AB41: 13.29 | AC41: 10.934891 | AD41: =M41-N41 -> 0.0079561939
A42: 42644 | B42: 0.026145557 | C42: -0.23916667 | D42: 0.029166667 | E42: 0.1075 | F42: 0.16 | G42: =0.3657*E42+(1-0.3657)*D42 -> 0.057813167 | H42: -4.3978395 | I42: 0.27825478 | J42: 2143.02 | K42: =-1+J42/J41 -> -0.0067989378 | L42: =L41*2/3+L44/3 -> 90.91 | M42: =L42/J42 -> 0.042421443 | N42: 0.033333333 | O42: 0.29248739 | P42: =F42-D42 -> 0.13083333 | Q42: =2*E42-F42-D42 -> 0.025833333 | R42: 0.017666667 | S42: =R42-N42 -> -0.015666667 | T42: =D42-B42 -> 0.0030211098 | U42: =P42-P41 -> 0.0125 | V42: =Q42-Q41 -> 0.0275 | W42: =H42-G42 -> -4.4556527 | X42: =I42-H42 -> 4.6760943 | Y42: =K42-I42 -> -0.28505372 | Z42: =D42-C42 -> 0.26833333 | AA42: =Z42-Z41 -> 0.040833333 | AB42: 17.06 | AC42: 25.165077 | AD42: =M42-N42 -> 0.0090881093
A43: 42675 | B43: 0.032781743 | C43: -0.23083333 | D43: 0.024166667 | E43: 0.12333333 | F43: 0.175 | G43: =0.3657*E43+(1-0.3657)*D43 -> 0.060431917 | H43: -1.5995748 | I43: -0.71222049 | J43: 2164.99 | K43: =-1+J43/J42 -> 0.010251888 | L43: =L41/3+L44*2/3 -> 92.73 | M43: =L43/J43 -> 0.042831607 | N43: 0.034166667 | O43: -0.93339875 | P43: =F43-D43 -> 0.15083333 | Q43: =2*E43-F43-D43 -> 0.0475 | R43: 0.017566667 | S43: =R43-N43 -> -0.0166 | T43: =D43-B43 -> -0.0086150758 | U43: =P43-P42 -> 0.02 | V43: =Q43-Q42 -> 0.021666667 | W43: =H43-G43 -> -1.6600067 | X43: =I43-H43 -> 0.8873543 | Y43: =K43-I43 -> 0.72247238 | Z43: =D43-C43 -> 0.255 | AA43: =Z43-Z42 -> -0.013333333 | AB43: 13.33 | AC43: -31.004141 | AD43: =M43-N43 -> 0.0086649399
A44: 42705 | B44: 0.028082435 | C44: -0.24666667 | D44: 0.015833333 | E44: 0.10833333 | F44: 0.16083333 | G44: =0.3657*E44+(1-0.3657)*D44 -> 0.049660583 | H44: 3.0000166 | I44: 2.1099425 | J44: 2246.63 | K44: =-1+J44/J43 -> 0.037709181 | L44: 94.55 | M44: =L44/J44 -> 0.042085257 | N44: 0.045 | O44: 2.8609361 | P44: =F44-D44 -> 0.145 | Q44: =2*E44-F44-D44 -> 0.04 | R44: 0.017708333 | S44: =R44-N44 -> -0.027291667 | T44: =D44-B44 -> -0.012249102 | U44: =P44-P43 -> -0.0058333333 | V44: =Q44-Q43 -> -0.0075 | W44: =H44-G44 -> 2.950356 | X44: =I44-H44 -> -0.89007406 | Y44: =K44-I44 -> -2.0722333 | Z44: =D44-C44 -> 0.2625 | AA44: =Z44-Z43 -> 0.0075 | AB44: 14.04 | AC44: -0.56657224 | AD44: =M44-N44 -> -0.0029147434
A45: 42736 | B45: 0.04029463 | C45: -0.25583333 | D45: 0.028333333 | E45: 0.12416667 | F45: 0.17583333 | G45: =0.3657*E45+(1-0.3657)*D45 -> 0.063379583 | H45: -1.4568783 | I45: 0.64683141 | J45: 2275.12 | K45: =-1+J45/J44 -> 0.012681216 | L45: =L44*2/3+L47/3 -> 96.463333 | M45: =L45/J45 -> 0.042399229 | N45: 0.054166667 | O45: -0.44945692 | P45: =F45-D45 -> 0.1475 | Q45: =2*E45-F45-D45 -> 0.044166667 | R45: 0.017791667 | S45: =R45-N45 -> -0.036375 | T45: =D45-B45 -> -0.011961297 | U45: =P45-P44 -> 0.0025 | V45: =Q45-Q44 -> 0.0041666667 | W45: =H45-G45 -> -1.5202579 | X45: =I45-H45 -> 2.1037098 | Y45: =K45-I45 -> -0.63415019 | Z45: =D45-C45 -> 0.28416667 | AA45: =Z45-Z44 -> 0.021666667 | AB45: 11.99 | AC45: -6.692607 | AD45: =M45-N45 -> -0.011767438
A46: 42767 | B46: 0.024709417 | C46: -0.2475 | D46: 0.011666667 | E46: 0.094166667 | F46: 0.15416667 | G46: =0.3657*E46+(1-0.3657)*D46 -> 0.041836917 | H46: 2.6768879 | I46: 1.1857445 | J46: 2329.91 | K46: =-1+J46/J45 -> 0.024082246 | L46: =L44/3+L47*2/3 -> 98.376667 | M46: =L46/J46 -> 0.042223376 | N46: 0.055 | O46: 2.5257043 | P46: =F46-D46 -> 0.1425 | Q46: =2*E46-F46-D46 -> 0.0225 | R46: 0.01755 | S46: =R46-N46 -> -0.03745 | T46: =D46-B46 -> -0.01304275 | U46: =P46-P45 -> -0.005 | V46: =Q46-Q45 -> -0.021666667 | W46: =H46-G46 -> 2.635051 | X46: =I46-H46 -> -1.4911434 | Y46: =K46-I46 -> -1.1616623 | Z46: =D46-C46 -> 0.25916667 | AA46: =Z46-Z45 -> -0.025 | AB46: 12.92 | AC46: 7.7564637 | AD46: =M46-N46 -> -0.012776624
A47: 42795 | B47: 0.033663127 | C47: -0.26833333 | D47: 0.014166667 | E47: 0.094166667 | F47: 0.1525 | G47: =0.3657*E47+(1-0.3657)*D47 -> 0.043422667 | H47: -0.13048189 | I47: -0.31338695 | J47: 2366.82 | K47: =-1+J47/J46 -> 0.015841814 | L47: 100.29 | M47: =L47/J47 -> 0.042373311 | N47: 0.065833333 | O47: 0.3219511 | P47: =F47-D47 -> 0.13833333 | Q47: =2*E47-F47-D47 -> 0.021666667 | R47: 0.017458333 | S47: =R47-N47 -> -0.048375 | T47: =D47-B47 -> -0.019496461 | U47: =P47-P46 -> -0.0041666667 | V47: =Q47-Q46 -> -0.00083333333 | W47: =H47-G47 -> -0.17390455 | X47: =I47-H47 -> -0.18290507 | Y47: =K47-I47 -> 0.32922877 | Z47: =D47-C47 -> 0.2825 | AA47: =Z47-Z46 -> 0.023333333 | AB47: 12.37 | AC47: 10.053381 | AD47: =M47-N47 -> -0.023460022
A48: 42826 | B48: 0.029944499 | C48: -0.25333333 | D48: 0.010833333 | E48: 0.0925 | F48: 0.1525 | G48: =0.3657*E48+(1-0.3657)*D48 -> 0.040698833 | H48: 0.76695809 | I48: 1.0510508 | J48: 2359.31 | K48: =-1+J48/J47 -> -0.0031730339 | L48: =L47*2/3+L50/3 -> 101.53333 | M48: =L48/J48 -> 0.043035181 | N48: 0.075 | O48: -0.38364686 | P48: =F48-D48 -> 0.14166667 | Q48: =2*E48-F48-D48 -> 0.021666667 | R48: 0.017616667 | S48: =R48-N48 -> -0.057383333 | T48: =D48-B48 -> -0.019111166 | U48: =P48-P47 -> 0.0033333333 | V48: =Q48-Q47 -> 3.469447e-17 | W48: =H48-G48 -> 0.72625926 | X48: =I48-H48 -> 0.28409275 | Y48: =K48-I48 -> -1.0542239 | Z48: =D48-C48 -> 0.26416667 | AA48: =Z48-Z47 -> -0.018333333 | AB48: 10.82 | AC48: -12.530315 | AD48: =M48-N48 -> -0.031964819
A49: 42856 | B49: 0.030672501 | C49: -0.24666667 | D49: 0.011666667 | E49: 0.089166667 | F49: 0.14916667 | G49: =0.3657*E49+(1-0.3657)*D49 -> 0.040008417 | H49: 1.5935076 | I49: 0.72617614 | J49: 2395.35 | K49: =-1+J49/J48 -> 0.015275653 | L49: =L47/3+L50*2/3 -> 102.77667 | M49: =L49/J49 -> 0.042906743 | N49: 0.075833333 | O49: 1.8101888 | P49: =F49-D49 -> 0.1375 | Q49: =2*E49-F49-D49 -> 0.0175 | R49: 0.017716667 | S49: =R49-N49 -> -0.058116667 | T49: =D49-B49 -> -0.019005834 | U49: =P49-P48 -> -0.0041666667 | V49: =Q49-Q48 -> -0.0041666667 | W49: =H49-G49 -> 1.5534992 | X49: =I49-H49 -> -0.86733149 | Y49: =K49-I49 -> -0.71090049 | Z49: =D49-C49 -> 0.25833333 | AA49: =Z49-Z48 -> -0.0058333333 | AB49: 10.41 | AC49: -2.5280899 | AD49: =M49-N49 -> -0.03292659
A50: 42887 | B50: 0.048586405 | C50: -0.22083333 | D50: 0.031666667 | E50: 0.10833333 | F50: 0.16333333 | G50: =0.3657*E50+(1-0.3657)*D50 -> 0.059703667 | H50: -1.2531727 | I50: 0.14213242 | J50: 2433.99 | K50: =-1+J50/J49 -> 0.016131254 | L50: 104.02 | M50: =L50/J50 -> 0.042736412 | N50: 0.086666667 | O50: -0.87392976 | P50: =F50-D50 -> 0.13166667 | Q50: =2*E50-F50-D50 -> 0.021666667 | R50: 0.017675 | S50: =R50-N50 -> -0.068991667 | T50: =D50-B50 -> -0.016919738 | U50: =P50-P49 -> -0.0058333333 | V50: =Q50-Q49 -> 0.0041666667 | W50: =H50-G50 -> -1.3128764 | X50: =I50-H50 -> 1.3953051 | Y50: =K50-I50 -> -0.12600116 | Z50: =D50-C50 -> 0.2525 | AA50: =Z50-Z49 -> -0.0058333333 | AB50: 11.18 | AC50: 11.02284 | AD50: =M50-N50 -> -0.043930254
A51: 42917 | B51: 0.041530849 | C51: -0.21916667 | D51: 0.025 | E51: 0.105 | F51: 0.16333333 | G51: =0.3657*E51+(1-0.3657)*D51 -> 0.054256 | H51: 1.0778075 | I51: 0.82148274 | J51: 2454.1 | K51: =-1+J51/J50 -> 0.0082621539 | L51: =L50*2/3+L53/3 -> 105.04 | M51: =L51/J51 -> 0.042801842 | N51: 0.095833333 | O51: 0.77913543 | P51: =F51-D51 -> 0.13833333 | Q51: =2*E51-F51-D51 -> 0.021666667 | R51: 0.0177 | S51: =R51-N51 -> -0.078133333 | T51: =D51-B51 -> -0.016530849 | U51: =P51-P50 -> 0.0066666667 | V51: =Q51-Q50 -> 0 | W51: =H51-G51 -> 1.0235515 | X51: =I51-H51 -> -0.25632477 | Y51: =K51-I51 -> -0.81322058 | Z51: =D51-C51 -> 0.24416667 | AA51: =Z51-Z50 -> -0.0083333333 | AB51: 10.26 | AC51: -8.5561497 | AD51: =M51-N51 -> -0.053031492
A52: 42948 | B52: 0.03510598 | C52: -0.23416667 | D52: 0.015833333 | E52: 0.09 | F52: 0.14916667 | G52: =0.3657*E52+(1-0.3657)*D52 -> 0.042956083 | H52: 0.92211165 | I52: -0.041057191 | J52: 2456.22 | K52: =-1+J52/J51 -> 0.00086386048 | L52: =L50/3+L53*2/3 -> 106.06 | M52: =L52/J52 -> 0.043180171 | N52: 0.096666667 | O52: 1.1252409 | P52: =F52-D52 -> 0.13333333 | Q52: =2*E52-F52-D52 -> 0.015 | R52: 0.017766667 | S52: =R52-N52 -> -0.0789 | T52: =D52-B52 -> -0.019272647 | U52: =P52-P51 -> -0.005 | V52: =Q52-Q51 -> -0.0066666667 | W52: =H52-G52 -> 0.87915557 | X52: =I52-H52 -> -0.96316885 | Y52: =K52-I52 -> 0.041921052 | Z52: =D52-C52 -> 0.25 | AA52: =Z52-Z51 -> 0.0058333333 | AB52: 10.59 | AC52: 5.5832502 | AD52: =M52-N52 -> -0.053486496
A53: 42979 | B53: 0.063443436 | C53: -0.21083333 | D53: 0.044166667 | E53: 0.11666667 | F53: 0.16666667 | G53: =0.3657*E53+(1-0.3657)*D53 -> 0.070679917 | H53: -1.9812762 | I53: 0.51526682 | J53: 2492.84 | K53: =-1+J53/J52 -> 0.014909088 | L53: 107.08 | M53: =L53/J53 -> 0.042955023 | N53: 0.095833333 | O53: -1.080143 | P53: =F53-D53 -> 0.1225 | Q53: =2*E53-F53-D53 -> 0.0225 | R53: 0.017691667 | S53: =R53-N53 -> -0.078141667 | T53: =D53-B53 -> -0.019276769 | U53: =P53-P52 -> -0.010833333 | V53: =Q53-Q52 -> 0.0075 | W53: =H53-G53 -> -2.0519561 | X53: =I53-H53 -> 2.496543 | Y53: =K53-I53 -> -0.50035774 | Z53: =D53-C53 -> 0.255 | AA53: =Z53-Z52 -> 0.005 | AB53: 9.51 | AC53: -6.1204344 | AD53: =M53-N53 -> -0.05287831
A54: 43009 | B54: 0.065022999 | C54: -0.20166667 | D54: 0.045 | E54: 0.11583333 | F54: 0.16666667 | G54: =0.3657*E54+(1-0.3657)*D54 -> 0.07090375 | H54: 0.41718511 | I54: 0.21338954 | J54: 2557 | K54: =-1+J54/J53 -> 0.025737713 | L54: =L53*2/3+L56/3 -> 108.01333 | M54: =L54/J54 -> 0.042242211 | N54: 0.095833333 | O54: 1.293308 | P54: =F54-D54 -> 0.12166667 | Q54: =2*E54-F54-D54 -> 0.02 | R54: 0.017583333 | S54: =R54-N54 -> -0.07825 | T54: =D54-B54 -> -0.020022999 | U54: =P54-P53 -> -0.00083333333 | V54: =Q54-Q53 -> -0.0025 | W54: =H54-G54 -> 0.34628136 | X54: =I54-H54 -> -0.20379557 | Y54: =K54-I54 -> -0.18765183 | Z54: =D54-C54 -> 0.24666667 | AA54: =Z54-Z53 -> -0.0083333333 | AB54: 10.18 | AC54: 5.7113188 | AD54: =M54-N54 -> -0.053591122
A55: 43040 | B55: 0.06879978 | C55: -0.19416667 | D55: 0.049166667 | E55: 0.115 | F55: 0.1625 | G55: =0.3657*E55+(1-0.3657)*D55 -> 0.073241917 | H55: -0.28095167 | I55: -0.27952825 | J55: 2593.61 | K55: =-1+J55/J54 -> 0.01431756 | L55: =L53/3+L56*2/3 -> 108.94667 | M55: =L55/J55 -> 0.042005801 | N55: 0.096666667 | O55: -0.34952012 | P55: =F55-D55 -> 0.11333333 | Q55: =2*E55-F55-D55 -> 0.018333333 | R55: 0.037441667 | S55: =R55-N55 -> -0.059225 | T55: =D55-B55 -> -0.019633113 | U55: =P55-P54 -> -0.0083333333 | V55: =Q55-Q54 -> -0.0016666667 | W55: =H55-G55 -> -0.35419359 | X55: =I55-H55 -> 0.0014234224 | Y55: =K55-I55 -> 0.29384581 | Z55: =D55-C55 -> 0.24333333 | AA55: =Z55-Z54 -> -0.0033333333 | AB55: 11.28 | AC55: 13.595166 | AD55: =M55-N55 -> -0.054660865
A56: 43070 | B56: 0.061174429 | C56: -0.19333333 | D56: 0.043333333 | E56: 0.105 | F56: 0.1525 | G56: =0.3657*E56+(1-0.3657)*D56 -> 0.065884833 | H56: 1.9238864 | I56: -0.11978702 | J56: 2664.34 | K56: =-1+J56/J55 -> 0.02727087 | L56: 109.88 | M56: =L56/J56 -> 0.041240983 | N56: 0.10833333 | O56: 2.1937669 | P56: =F56-D56 -> 0.10916667 | Q56: =2*E56-F56-D56 -> 0.014166667 | R56: 0.038491667 | S56: =R56-N56 -> -0.069841667 | T56: =D56-B56 -> -0.017841096 | U56: =P56-P55 -> -0.0041666667 | V56: =Q56-Q55 -> -0.0041666667 | W56: =H56-G56 -> 1.8580016 | X56: =I56-H56 -> -2.0436735 | Y56: =K56-I56 -> 0.14705789 | Z56: =D56-C56 -> 0.23666667 | AA56: =Z56-Z55 -> -0.0066666667 | AB56: 11.04 | AC56: -3.4120735 | AD56: =M56-N56 -> -0.067092351
A57: 43101 | B57: 0.080475613 | C57: -0.1775 | D57: 0.0675 | E57: 0.12916667 | F57: 0.16583333 | G57: =0.3657*E57+(1-0.3657)*D57 -> 0.0900515 | H57: -0.79771731 | I57: 0.15419726 | J57: 2789.8 | K57: =-1+J57/J56 -> 0.047088585 | L57: =L56*2/3+L59/3 -> 111.73333 | M57: =L57/J57 -> 0.040050661 | N57: 0.1175 | O57: -0.70844611 | P57: =F57-D57 -> 0.098333333 | Q57: =2*E57-F57-D57 -> 0.025 | R57: 0.038591667 | S57: =R57-N57 -> -0.078908333 | T57: =D57-B57 -> -0.012975613 | U57: =P57-P56 -> -0.010833333 | V57: =Q57-Q56 -> 0.010833333 | W57: =H57-G57 -> -0.88776881 | X57: =I57-H57 -> 0.95191457 | Y57: =K57-I57 -> -0.10710867 | Z57: =D57-C57 -> 0.245 | AA57: =Z57-Z56 -> 0.0083333333 | AB57: 13.58 | AC57: 48.415301 | AD57: =M57-N57 -> -0.077449339
A58: 43132 | B58: 0.083726297 | C58: -0.165 | D58: 0.07 | E58: 0.13083333 | F58: 0.165 | G58: =0.3657*E58+(1-0.3657)*D58 -> 0.09224675 | H58: -1.2847047 | I58: -0.6959731 | J58: 2705.16 | K58: =-1+J58/J57 -> -0.030339092 | L58: =L56/3+L59*2/3 -> 113.58667 | M58: =L58/J58 -> 0.04198889 | N58: 0.11833333 | O58: -1.1425692 | P58: =F58-D58 -> 0.095 | Q58: =2*E58-F58-D58 -> 0.026666667 | R58: 0.038616667 | S58: =R58-N58 -> -0.079716667 | T58: =D58-B58 -> -0.013726297 | U58: =P58-P57 -> -0.0033333333 | V58: =Q58-Q57 -> 0.0016666667 | W58: =H58-G58 -> -1.3769514 | X58: =I58-H58 -> 0.58873158 | Y58: =K58-I58 -> 0.66563401 | Z58: =D58-C58 -> 0.235 | AA58: =Z58-Z57 -> -0.01 | AB58: 19.85 | AC58: 46.170839 | AD58: =M58-N58 -> -0.076344443
A59: 43160 | B59: 0.080496559 | C59: -0.18916667 | D59: 0.071666667 | E59: 0.11833333 | F59: 0.14666667 | G59: =0.3657*E59+(1-0.3657)*D59 -> 0.088732667 | H59: 0.29010016 | I59: -0.46623483 | J59: 2702.77 | K59: =-1+J59/J58 -> -0.00088349672 | L59: 115.44 | M59: =L59/J59 -> 0.042711736 | N59: 0.12583333 | O59: -1.4912303 | P59: =F59-D59 -> 0.075 | Q59: =2*E59-F59-D59 -> 0.018333333 | R59: 0.038641667 | S59: =R59-N59 -> -0.087191667 | T59: =D59-B59 -> -0.0088298925 | U59: =P59-P58 -> -0.02 | V59: =Q59-Q58 -> -0.0083333333 | W59: =H59-G59 -> 0.2013675 | X59: =I59-H59 -> -0.756335 | Y59: =K59-I59 -> 0.46535134 | Z59: =D59-C59 -> 0.26083333 | AA59: =Z59-Z58 -> 0.025833333 | AB59: 19.97 | AC59: 1.9397652 | AD59: =M59-N59 -> -0.083121597
A60: 43191 | B60: 0.075013888 | C60: -0.17916667 | D60: 0.069166667 | E60: 0.12583333 | F60: 0.15666667 | G60: =0.3657*E60+(1-0.3657)*D60 -> 0.089889667 | H60: 0.21720707 | I60: 0.58200758 | J60: 2653.63 | K60: =-1+J60/J59 -> -0.018181347 | L60: =L59*2/3+L62/3 -> 117.78667 | M60: =L60/J60 -> 0.044386997 | N60: 0.14083333 | O60: 2.4711223 | P60: =F60-D60 -> 0.0875 | Q60: =2*E60-F60-D60 -> 0.025833333 | R60: 0.038475 | S60: =R60-N60 -> -0.10235833 | T60: =D60-B60 -> -0.005847221 | U60: =P60-P59 -> 0.0125 | V60: =Q60-Q59 -> 0.0075 | W60: =H60-G60 -> 0.1273174 | X60: =I60-H60 -> 0.36480051 | Y60: =K60-I60 -> -0.60018892 | Z60: =D60-C60 -> 0.24833333 | AA60: =Z60-Z59 -> -0.0125 | AB60: 15.93 | AC60: -24.50237 | AD60: =M60-N60 -> -0.096446336
A61: 43221 | B61: 0.067723719 | C61: -0.19916667 | D61: 0.055 | E61: 0.11083333 | F61: 0.14666667 | G61: =0.3657*E61+(1-0.3657)*D61 -> 0.07541825 | H61: -0.29605568 | I61: -0.17655457 | J61: 2701.49 | K61: =-1+J61/J60 -> 0.018035672 | L61: =L59/3+L62*2/3 -> 120.13333 | M61: =L61/J61 -> 0.044469287 | N61: 0.14166667 | O61: 1.5632379 | P61: =F61-D61 -> 0.091666667 | Q61: =2*E61-F61-D61 -> 0.02 | R61: 0.037741667 | S61: =R61-N61 -> -0.103925 | T61: =D61-B61 -> -0.012723719 | U61: =P61-P60 -> 0.0041666667 | V61: =Q61-Q60 -> -0.0058333333 | W61: =H61-G61 -> -0.37147393 | X61: =I61-H61 -> 0.1195011 | Y61: =K61-I61 -> 0.19459024 | Z61: =D61-C61 -> 0.25416667 | AA61: =Z61-Z60 -> 0.0058333333 | AB61: 15.43 | AC61: -2.9559748 | AD61: =M61-N61 -> -0.09719738
A62: 43252 | B62: 0.074083933 | C62: -0.18416667 | D62: 0.064166667 | E62: 0.11583333 | F62: 0.14916667 | G62: =0.3657*E62+(1-0.3657)*D62 -> 0.083061167 | H62: -0.33014033 | I62: -0.43699005 | J62: 2754.35 | K62: =-1+J62/J61 -> 0.01956698 | L62: 122.48 | M62: =L62/J62 -> 0.044467842 | N62: 0.15166667 | O62: 0.17050584 | P62: =F62-D62 -> 0.085 | Q62: =2*E62-F62-D62 -> 0.018333333 | R62: 0.037558333 | S62: =R62-N62 -> -0.11410833 | T62: =D62-B62 -> -0.0099172664 | U62: =P62-P61 -> -0.0066666667 | V62: =Q62-Q61 -> -0.0016666667 | W62: =H62-G62 -> -0.4132015 | X62: =I62-H62 -> -0.10684972 | Y62: =K62-I62 -> 0.45655703 | Z62: =D62-C62 -> 0.24833333 | AA62: =Z62-Z61 -> -0.0058333333 | AB62: 16.09 | AC62: 26.295133 | AD62: =M62-N62 -> -0.10719882
A63: 43282 | B63: 0.081397995 | C63: -0.1775 | D63: 0.069166667 | E63: 0.12 | F63: 0.1525 | G63: =0.3657*E63+(1-0.3657)*D63 -> 0.087756417 | H63: 0.34295358 | I63: 1.5605509 | J63: 2793.64 | K63: =-1+J63/J62 -> 0.014264709 | L63: =L62*2/3+L65/3 -> 125.11667 | M63: =L63/J63 -> 0.044786253 | N63: 0.15916667 | O63: 1.3282751 | P63: =F63-D63 -> 0.083333333 | Q63: =2*E63-F63-D63 -> 0.018333333 | R63: 0.037875 | S63: =R63-N63 -> -0.12129167 | T63: =D63-B63 -> -0.012231328 | U63: =P63-P62 -> -0.0016666667 | V63: =Q63-Q62 -> 0 | W63: =H63-G63 -> 0.25519716 | X63: =I63-H63 -> 1.2175974 | Y63: =K63-I63 -> -1.5462862 | Z63: =D63-C63 -> 0.24666667 | AA63: =Z63-Z62 -> -0.0016666667 | AB63: 12.83 | AC63: -20.508055 | AD63: =M63-N63 -> -0.11438041
A64: 43313 | B64: 0.080406711 | C64: -0.18333333 | D64: 0.068333333 | E64: 0.1175 | F64: 0.1525 | G64: =0.3657*E64+(1-0.3657)*D64 -> 0.086313583 | H64: 0.63164198 | I64: 0.19739749 | J64: 2857.82 | K64: =-1+J64/J63 -> 0.022973611 | L64: =L62/3+L65*2/3 -> 127.75333 | M64: =L64/J64 -> 0.044703072 | N64: 0.15916667 | O64: 0.013361897 | P64: =F64-D64 -> 0.084166667 | Q64: =2*E64-F64-D64 -> 0.014166667 | R64: 0.057591667 | S64: =R64-N64 -> -0.101575 | T64: =D64-B64 -> -0.012073378 | U64: =P64-P63 -> 0.00083333333 | V64: =Q64-Q63 -> -0.0041666667 | W64: =H64-G64 -> 0.54532839 | X64: =I64-H64 -> -0.43424449 | Y64: =K64-I64 -> -0.17442388 | Z64: =D64-C64 -> 0.25166667 | AA64: =Z64-Z63 -> 0.005 | AB64: 12.86 | AC64: 14.108252 | AD64: =M64-N64 -> -0.11446359
A65: 43344 | B65: 0.088141978 | C65: -0.19583333 | D65: 0.078333333 | E65: 0.13083333 | F65: 0.16416667 | G65: =0.3657*E65+(1-0.3657)*D65 -> 0.097532583 | H65: -1.1011759 | I65: 0.27039545 | J65: 2901.5 | K65: =-1+J65/J64 -> 0.015284378 | L65: 130.39 | M65: =L65/J65 -> 0.044938825 | N65: 0.1625 | O65: 0.0451621 | P65: =F65-D65 -> 0.085833333 | Q65: =2*E65-F65-D65 -> 0.019166667 | R65: 0.058433333 | S65: =R65-N65 -> -0.10406667 | T65: =D65-B65 -> -0.0098086447 | U65: =P65-P64 -> 0.0016666667 | V65: =Q65-Q64 -> 0.005 | W65: =H65-G65 -> -1.1987084 | X65: =I65-H65 -> 1.3715713 | Y65: =K65-I65 -> -0.25511107 | Z65: =D65-C65 -> 0.27416667 | AA65: =Z65-Z64 -> 0.0225 | AB65: 12.12 | AC65: -5.7542768 | AD65: =M65-N65 -> -0.11756118
A66: 43374 | B66: 0.083251526 | C66: -0.18333333 | D66: 0.068333333 | E66: 0.11916667 | F66: 0.15916667 | G66: =0.3657*E66+(1-0.3657)*D66 -> 0.086923083 | H66: 0.29058104 | I66: -1.6933105 | J66: 2785.46 | K66: =-1+J66/J65 -> -0.039993107 | L66: =L65*2/3+L68/3 -> 131.05667 | M66: =L66/J66 -> 0.047050278 | N66: 0.1825 | O66: -2.5280473 | P66: =F66-D66 -> 0.090833333 | Q66: =2*E66-F66-D66 -> 0.010833333 | R66: 0.058425 | S66: =R66-N66 -> -0.124075 | T66: =D66-B66 -> -0.014918192 | U66: =P66-P65 -> 0.005 | V66: =Q66-Q65 -> -0.0083333333 | W66: =H66-G66 -> 0.20365796 | X66: =I66-H66 -> -1.9838916 | Y66: =K66-I66 -> 1.6533174 | Z66: =D66-C66 -> 0.25166667 | AA66: =Z66-Z65 -> -0.0225 | AB66: 21.23 | AC66: 49.296765 | AD66: =M66-N66 -> -0.13544972
A67: 43405 | B67: 0.081108849 | C67: -0.195 | D67: 0.065833333 | E67: 0.11416667 | F67: 0.17416667 | G67: =0.3657*E67+(1-0.3657)*D67 -> 0.083508833 | H67: -2.1070181 | I67: -1.0701034 | J67: 2723.23 | K67: =-1+J67/J66 -> -0.022341014 | L67: =L65/3+L68*2/3 -> 131.72333 | M67: =L67/J67 -> 0.048370256 | N67: 0.18333333 | O67: -0.85098504 | P67: =F67-D67 -> 0.10833333 | Q67: =2*E67-F67-D67 -> -0.011666667 | R67: 0.058475 | S67: =R67-N67 -> -0.12485833 | T67: =D67-B67 -> -0.015275516 | U67: =P67-P66 -> 0.0175 | V67: =Q67-Q66 -> -0.0225 | W67: =H67-G67 -> -2.1905269 | X67: =I67-H67 -> 1.0369147 | Y67: =K67-I67 -> 1.0477624 | Z67: =D67-C67 -> 0.26083333 | AA67: =Z67-Z66 -> 0.0091666667 | AB67: 18.07 | AC67: -7.3808303 | AD67: =M67-N67 -> -0.13496308
A68: 43435 | B68: 0.077562004 | C68: -0.20666667 | D68: 0.064166667 | E68: 0.10916667 | F68: 0.15583333 | G68: =0.3657*E68+(1-0.3657)*D68 -> 0.080623167 | H68: 1.4384825 | I68: -1.4043308 | J68: 2567.31 | K68: =-1+J68/J67 -> -0.057255538 | L68: 132.39 | M68: =L68/J68 -> 0.051567594 | N68: 0.18916667 | O68: -2.5046977 | P68: =F68-D68 -> 0.091666667 | Q68: =2*E68-F68-D68 -> -0.0016666667 | R68: 0.05855 | S68: =R68-N68 -> -0.13061667 | T68: =D68-B68 -> -0.013395337 | U68: =P68-P67 -> -0.016666667 | V68: =Q68-Q67 -> 0.01 | W68: =H68-G68 -> 1.3578594 | X68: =I68-H68 -> -2.8428133 | Y68: =K68-I68 -> 1.3470753 | Z68: =D68-C68 -> 0.27083333 | AA68: =Z68-Z67 -> 0.01 | AB68: 25.42 | AC68: 40.675152 | AD68: =M68-N68 -> -0.13759907
A69: 43678 | B69: 0.034533037 | C69: -0.26333333 | D69: 0.028333333 | E69: 0.036666667 | F69: 0.084166667 | G69: =0.3657*E69+(1-0.3657)*D69 -> 0.031380833 | H69: 1.099245 | I69: 0.54041365 | J69: 2897.4982 | K69: =-1+J69/J68 -> 0.12861251 | L69: =L67/3+L70*2/3 -> 132.50778 | M69: =L69/J69 -> 0.04573179 | N69: 0.1775 | O69: -1.2793531 | P69: =F69-D69 -> 0.055833333 | Q69: =2*E69-F69-D69 -> -0.039166667 | R69: 0.059175 | S69: =R69-N69 -> -0.118325 | T69: =D69-B69 -> -0.0061997041 | U69: =P69-P68 -> -0.035833333 | V69: =Q69-Q68 -> -0.0375 | W69: =H69-G69 -> 1.0678641 | X69: =I69-H69 -> -0.55883133 | Y69: =K69-I69 -> -0.41180114 | Z69: =D69-C69 -> 0.29166667 | AA69: =Z69-Z68 -> 0.020833333 | AB69: 18.98 | AC69: -22.814152 | AD69: =M69-N69 -> -0.13176821
A70: 43709 | B70: 0.033571798 | C70: -0.27416667 | D70: 0.023333333 | E70: 0.038333333 | F70: 0.081666667 | G70: =0.3657*E70+(1-0.3657)*D70 -> 0.028818833 | H70: 0.024756663 | I70: -0.069943023 | J70: 2982.156 | K70: =-1+J70/J69 -> 0.029217557 | L70: 132.9 | M70: =L70/J70 -> 0.044565073 | N70: 0.17 | O70: 1.3201729 | P70: =F70-D70 -> 0.058333333 | Q70: =2*E70-F70-D70 -> -0.028333333 | R70: 0.05915 | S70: =R70-N70 -> -0.11085 | T70: =D70-B70 -> -0.010238465 | U70: =P70-P69 -> 0.0025 | V70: =Q70-Q69 -> 0.010833333 | W70: =H70-G70 -> -0.0040621699 | X70: =I70-H70 -> -0.094699686 | Y70: =K70-I70 -> 0.09916058 | Z70: =D70-C70 -> 0.2975 | AA70: =Z70-Z69 -> 0.0058333333 | AB70: 16.24 | AC70: -17.395727 | AD70: =M70-N70 -> -0.12543493
A71: 43739 | B71: 0.043908615 | C71: -0.21916667 | D71: 0.035 | E71: 0.05 | F71: 0.095 | G71: =0.3657*E71+(1-0.3657)*D71 -> 0.0404855 | H71: -0.21292051 | I71: 0.10415198 | J71: 2977.68 | K71: =-1+J71/J70 -> -0.0015009275 | L71: =L70*2/3+L73/3 -> 135.09 | M71: =L71/J71 -> 0.045367534 | N71: 0.1525 | O71: -0.83998799 | P71: =F71-D71 -> 0.06 | Q71: =2*E71-F71-D71 -> -0.03 | R71: 0.059233333 | S71: =R71-N71 -> -0.093266667 | T71: =D71-B71 -> -0.0089086152 | U71: =P71-P70 -> 0.0016666667 | V71: =Q71-Q70 -> -0.0016666667 | W71: =H71-G71 -> -0.25340601 | X71: =I71-H71 -> 0.31707249 | Y71: =K71-I71 -> -0.10565291 | Z71: =D71-C71 -> 0.25416667 | AA71: =Z71-Z70 -> -0.043333333 | AB71: 13.22 | AC71: -22.41784 | AD71: =M71-N71 -> -0.10713247
A72: 43770 | B72: 0.048308012 | C72: -0.20333333 | D72: 0.041666667 | E72: 0.056666667 | F72: 0.10083333 | G72: =0.3657*E72+(1-0.3657)*D72 -> 0.047152167 | H72: -0.15656717 | I72: 0.70032983 | J72: 3104.9045 | K72: =-1+J72/J71 -> 0.042726048 | L72: =L70/3+L73*2/3 -> 137.28 | M72: =L72/J72 -> 0.04421392 | N72: 0.12916667 | O72: 1.3072998 | P72: =F72-D72 -> 0.059166667 | Q72: =2*E72-F72-D72 -> -0.029166667 | R72: 0.059208333 | S72: =R72-N72 -> -0.069958333 | T72: =D72-B72 -> -0.0066413449 | U72: =P72-P71 -> -0.00083333333 | V72: =Q72-Q71 -> 0.00083333333 | W72: =H72-G72 -> -0.20371934 | X72: =I72-H72 -> 0.856897 | Y72: =K72-I72 -> -0.65760378 | Z72: =D72-C72 -> 0.245 | AA72: =Z72-Z71 -> -0.0091666667 | AB72: 12.62 | AC72: 2.601626 | AD72: =M72-N72 -> -0.084952746
A73: 43800 | B73: 0.05316067 | C73: -0.20333333 | D73: 0.044166667 | E73: 0.068333333 | F73: 0.11166667 | G73: =0.3657*E73+(1-0.3657)*D73 -> 0.053004417 | H73: -0.01503251 | I73: 1.3420566 | J73: 3176.7495 | K73: =-1+J73/J72 -> 0.023139206 | L73: 139.47 | M73: =L73/J73 -> 0.043903367 | N73: 0.12916667 | O73: 0.79930043 | P73: =F73-D73 -> 0.0675 | Q73: =2*E73-F73-D73 -> -0.019166667 | R73: 0.059175 | S73: =R73-N73 -> -0.069991667 | T73: =D73-B73 -> -0.0089940034 | U73: =P73-P72 -> 0.0083333333 | V73: =Q73-Q72 -> 0.01 | W73: =H73-G73 -> -0.068036927 | X73: =I73-H73 -> 1.3570891 | Y73: =K73-I73 -> -1.3189174 | Z73: =D73-C73 -> 0.2475 | AA73: =Z73-Z72 -> 0.0025 | AB73: 13.78 | AC73: -13.659148 | AD73: =M73-N73 -> -0.0852633
A74: 43831 | B74: 0.038702133 | C74: -0.2125 | D74: 0.034166667 | E74: 0.044166667 | F74: 0.085833333 | G74: =0.3657*E74+(1-0.3657)*D74 -> 0.037823667 | H74: 3.1376304 | I74: -0.40229332 | J74: 3278.2029 | K74: =-1+J74/J73 -> 0.031936208 | L74: =L73*2/3+L76/3 -> 131.75667 | M74: =L74/J74 -> 0.040191737 | N74: 0.12916667 | O74: -0.02109395 | P74: =F74-D74 -> 0.051666667 | Q74: =2*E74-F74-D74 -> -0.031666667 | R74: 0.059275 | S74: =R74-N74 -> -0.069891667 | T74: =D74-B74 -> -0.0045354667 | U74: =P74-P73 -> -0.015833333 | V74: =Q74-Q73 -> -0.0125 | W74: =H74-G74 -> 3.0998067 | X74: =I74-H74 -> -3.5399237 | Y74: =K74-I74 -> 0.43422953 | Z74: =D74-C74 -> 0.24666667 | AA74: =Z74-Z73 -> -0.00083333333 | AB74: 18.84 | AC74: 34.379458 | AD74: =M74-N74 -> -0.08897493
A75: 43862 | B75: 0.029348789 | C75: -0.20916667 | D75: 0.025 | E75: 0.035833333 | F75: 0.078333333 | G75: =0.3657*E75+(1-0.3657)*D75 -> 0.02896175 | H75: -1.5466792 | I75: -1.3992042 | J75: 3277.3142 | K75: =-1+J75/J74 -> -0.00027107737 | L75: =L73/3+L76*2/3 -> 124.04333 | M75: =L75/J75 -> 0.037849082 | N75: 0.13166667 | O75: -4.1526948 | P75: =F75-D75 -> 0.053333333 | Q75: =2*E75-F75-D75 -> -0.031666667 | R75: 0.0592 | S75: =R75-N75 -> -0.072466667 | T75: =D75-B75 -> -0.004348789 | U75: =P75-P74 -> 0.0016666667 | V75: =Q75-Q74 -> 0 | W75: =H75-G75 -> -1.575641 | X75: =I75-H75 -> 0.14747498 | Y75: =K75-I75 -> 1.3989331 | Z75: =D75-C75 -> 0.23416667 | AA75: =Z75-Z74 -> -0.0125 | AB75: 40.11 | AC75: 112.89809 | AD75: =M75-N75 -> -0.093817585
A76: 43891 | B76: 0.014933255 | C76: -0.20916667 | D76: 0.0125 | E76: 0.03 | F76: 0.071666667 | G76: =0.3657*E76+(1-0.3657)*D76 -> 0.01889975 | H76: -6.5704971 | I76: -12.406723 | J76: 2652.3936 | K76: =-1+J76/J75 -> -0.1906807 | L76: 116.33 | M76: =L76/J76 -> 0.043858498 | N76: 0.054166667 | O76: -7.0047285 | P76: =F76-D76 -> 0.059166667 | Q76: =2*E76-F76-D76 -> -0.024166667 | R76: 0.0266 | S76: =R76-N76 -> -0.027566667 | T76: =D76-B76 -> -0.0024332552 | U76: =P76-P75 -> 0.0058333333 | V76: =Q76-Q75 -> 0.0075 | W76: =H76-G76 -> -6.5893968 | X76: =I76-H76 -> -5.8362259 | Y76: =K76-I76 -> 12.216042 | Z76: =D76-C76 -> 0.22166667 | AA76: =Z76-Z75 -> -0.0125 | AB76: 53.54 | AC76: 67.364802 | AD76: =M76-N76 -> -0.010308169
A77: 43922 | B77: 0.0092215606 | C77: -0.20083333 | D77: 0.0033333333 | E77: 0.02 | F77: 0.050833333 | G77: =0.3657*E77+(1-0.3657)*D77 -> 0.0094283333 | H77: 7.375987 | I77: 5.5398239 | J77: 2761.9752 | K77: =-1+J77/J76 -> 0.04131423 | L77: =L76*2/3+L79/3 -> 110.63 | M77: =L77/J77 -> 0.040054668 | N77: 0.0041666667 | O77: 4.5018822 | P77: =F77-D77 -> 0.0475 | Q77: =2*E77-F77-D77 -> -0.014166667 | R77: 0.0054916667 | S77: =R77-N77 -> 0.001325 | T77: =D77-B77 -> -0.0058882273 | U77: =P77-P76 -> -0.011666667 | V77: =Q77-Q76 -> 0.01 | W77: =H77-G77 -> 7.3665587 | X77: =I77-H77 -> -1.8361632 | Y77: =K77-I77 -> -5.4985096 | Z77: =D77-C77 -> 0.20416667 | AA77: =Z77-Z76 -> -0.0175 | AB77: 34.15 | AC77: -32.920841 | AD77: =M77-N77 -> 0.035888001
A78: 43952 | B78: -0.00015163443 | C78: -0.23833333 | D78: -0.0041666667 | E78: 0.015 | F78: 0.05 | G78: =0.3657*E78+(1-0.3657)*D78 -> 0.0028425833 | H78: 1.0945044 | I78: 3.3015689 | J78: 2919.615 | K78: =-1+J78/J77 -> 0.057075009 | L78: =L76/3+L79*2/3 -> 104.93 | M78: =L78/J78 -> 0.03593967 | N78: 0.0041666667 | O78: 2.7070181 | P78: =F78-D78 -> 0.054166667 | Q78: =2*E78-F78-D78 -> -0.015833333 | R78: 0.0056166667 | S78: =R78-N78 -> 0.00145 | T78: =D78-B78 -> -0.0040150322 | U78: =P78-P77 -> 0.0066666667 | V78: =Q78-Q77 -> -0.0016666667 | W78: =H78-G78 -> 1.0916618 | X78: =I78-H78 -> 2.2070645 | Y78: =K78-I78 -> -3.2444939 | Z78: =D78-C78 -> 0.23416667 | AA78: =Z78-Z77 -> 0.03 | AB78: 27.51 | AC78: -26.028502 | AD78: =M78-N78 -> 0.031773003
A79: 43983 | B79: -0.0026057085 | C79: -0.22916667 | D79: -0.0075 | E79: 0.015833333 | F79: 0.055 | G79: =0.3657*E79+(1-0.3657)*D79 -> 0.001033 | H79: 1.0174081 | I79: 1.0358803 | J79: 3104.6609 | K79: =-1+J79/J78 -> 0.063380243 | L79: 99.23 | M79: =L79/J79 -> 0.031961623 | N79: 0.0066666667 | O79: 1.45706 | P79: =F79-D79 -> 0.0625 | Q79: =2*E79-F79-D79 -> -0.015833333 | R79: 0.0053833333 | S79: =R79-N79 -> -0.0012833333 | T79: =D79-B79 -> -0.0048942915 | U79: =P79-P78 -> 0.0083333333 | V79: =Q79-Q78 -> 0 | W79: =H79-G79 -> 1.0163751 | X79: =I79-H79 -> 0.018472121 | Y79: =K79-I79 -> -0.97250002 | Z79: =D79-C79 -> 0.22166667 | AA79: =Z79-Z78 -> -0.0125 | AB79: 30.43 | AC79: 18.589244 | AD79: =M79-N79 -> 0.025294956
A80: 44013 | B80: -0.0065989266 | C80: -0.2475 | D80: -0.010833333 | E80: 0.010833333 | F80: 0.051666667 | G80: =0.3657*E80+(1-0.3657)*D80 -> -0.0029098333 | H80: 2.1406602 | I80: 2.9493873 | J80: 3207.6191 | K80: =-1+J80/J79 -> 0.033162456 | L80: =L79*2/3+L82/3 -> 98.893333 | M80: =L80/J80 -> 0.03083076 | N80: 0.0075 | O80: -0.45287219 | P80: =F80-D80 -> 0.0625 | Q80: =2*E80-F80-D80 -> -0.019166667 | R80: 0.0049916667 | S80: =R80-N80 -> -0.0025083333 | T80: =D80-B80 -> -0.0042344068 | U80: =P80-P79 -> 0 | V80: =Q80-Q79 -> -0.0033333333 | W80: =H80-G80 -> 2.14357 | X80: =I80-H80 -> 0.80872712 | Y80: =K80-I80 -> -2.9162249 | Z80: =D80-C80 -> 0.23666667 | AA80: =Z80-Z79 -> 0.015 | AB80: 24.46 | AC80: -12.455261 | AD80: =M80-N80 -> 0.02333076
A81: 44044 | B81: -0.0027917188 | C81: -0.265 | D81: -0.0058333333 | E81: 0.029166667 | F81: 0.074166667 | G81: =0.3657*E81+(1-0.3657)*D81 -> 0.0069661667 | H81: -1.1978012 | I81: 1.1486624 | J81: 3391.71 | K81: =-1+J81/J80 -> 0.057391761 | L81: =L79/3+L82*2/3 -> 98.556667 | M81: =L81/J81 -> 0.029058105 | N81: 0.0083333333 | O81: 1.4746502 | P81: =F81-D81 -> 0.08 | Q81: =2*E81-F81-D81 -> -0.01 | R81: 0.0046833333 | S81: =R81-N81 -> -0.00365 | T81: =D81-B81 -> -0.0030416146 | U81: =P81-P80 -> 0.0175 | V81: =Q81-Q80 -> 0.0091666667 | W81: =H81-G81 -> -1.2047674 | X81: =I81-H81 -> 2.3464636 | Y81: =K81-I81 -> -1.0912707 | Z81: =D81-C81 -> 0.25916667 | AA81: =Z81-Z80 -> 0.0225 | AB81: 26.41 | AC81: 11.153199 | AD81: =M81-N81 -> 0.020724772
A82: 44075 | B82: -0.0052194629 | C82: -0.26083333 | D82: -0.0066666667 | E82: 0.021666667 | F82: 0.064166667 | G82: =0.3657*E82+(1-0.3657)*D82 -> 0.0036948333 | H82: 0.0017479164 | I82: -1.1547202 | J82: 3365.5167 | K82: =-1+J82/J81 -> -0.0077227515 | L82: 98.22 | M82: =L82/J82 -> 0.029184226 | N82: 0.0075 | O82: -0.32059917 | P82: =F82-D82 -> 0.070833333 | Q82: =2*E82-F82-D82 -> -0.014166667 | R82: 0.0045583333 | S82: =R82-N82 -> -0.0029416667 | T82: =D82-B82 -> -0.0014472038 | U82: =P82-P81 -> -0.0091666667 | V82: =Q82-Q81 -> -0.0041666667 | W82: =H82-G82 -> -0.001946917 | X82: =I82-H82 -> -1.1564681 | Y82: =K82-I82 -> 1.1469975 | Z82: =D82-C82 -> 0.25416667 | AA82: =Z82-Z81 -> -0.005 | AB82: 26.37 | AC82: -0.75272864 | AD82: =M82-N82 -> 0.021684226
A83: 44105 | B83: -0.0034447301 | C83: -0.26416667 | D83: -0.0058333333 | E83: 0.025 | F83: 0.068333333 | G83: =0.3657*E83+(1-0.3657)*D83 -> 0.0054424167 | H83: 0.29524176 | I83: 0.00086050517 | J83: 3418.7014 | K83: =-1+J83/J82 -> 0.015802833 | L83: =L82*2/3+L85/3 -> 96.856667 | M83: =L83/J83 -> 0.028331421 | N83: 0.0075 | O83: -1.9001782 | P83: =F83-D83 -> 0.074166667 | Q83: =2*E83-F83-D83 -> -0.0125 | R83: 0.0044833333 | S83: =R83-N83 -> -0.0030166667 | T83: =D83-B83 -> -0.0023886033 | U83: =P83-P82 -> 0.0033333333 | V83: =Q83-Q82 -> 0.0016666667 | W83: =H83-G83 -> 0.28979934 | X83: =I83-H83 -> -0.29438125 | Y83: =K83-I83 -> 0.014942328 | Z83: =D83-C83 -> 0.25833333 | AA83: =Z83-Z82 -> 0.0041666667 | AB83: 38.02 | AC83: 35.979971 | AD83: =M83-N83 -> 0.020831421
A84: 44136 | B84: -0.00014957775 | C84: -0.26083333 | D84: -0.0016666667 | E84: 0.03 | F84: 0.070833333 | G84: =0.3657*E84+(1-0.3657)*D84 -> 0.0099138333 | H84: 2.3738191 | I84: 4.1964629 | J84: 3548.9925 | K84: =-1+J84/J83 -> 0.038111295 | L84: =L82/3+L85*2/3 -> 95.493333 | M84: =L84/J84 -> 0.026907167 | N84: 0.0075 | O84: 5.5867023 | P84: =F84-D84 -> 0.0725 | Q84: =2*E84-F84-D84 -> -0.0091666667 | R84: 0.004475 | S84: =R84-N84 -> -0.003025 | T84: =D84-B84 -> -0.0015170889 | U84: =P84-P83 -> -0.0016666667 | V84: =Q84-Q83 -> 0.0033333333 | W84: =H84-G84 -> 2.3639052 | X84: =I84-H84 -> 1.8226438 | Y84: =K84-I84 -> -4.1583516 | Z84: =D84-C84 -> 0.25916667 | AA84: =Z84-Z83 -> 0.00083333333 | AB84: 20.57 | AC84: -44.600054 | AD84: =M84-N84 -> 0.019407167
A85: 44166 | B85: -0.0041351729 | C85: -0.25916667 | D85: -0.01 | E85: 0.019166667 | F85: 0.06 | G85: =0.3657*E85+(1-0.3657)*D85 -> 0.00066625 | H85: 1.5496803 | I85: 1.1870721 | J85: 3695.31 | K85: =-1+J85/J84 -> 0.041227898 | L85: 94.13 | M85: =L85/J85 -> 0.025472829 | N85: 0.0075 | O85: 1.8519535 | P85: =F85-D85 -> 0.07 | Q85: =2*E85-F85-D85 -> -0.011666667 | R85: 0.0041 | S85: =R85-N85 -> -0.0034 | T85: =D85-B85 -> -0.0058648271 | U85: =P85-P84 -> -0.0025 | V85: =Q85-Q84 -> -0.0025 | W85: =H85-G85 -> 1.5490141 | X85: =I85-H85 -> -0.36260824 | Y85: =K85-I85 -> -1.1458442 | Z85: =D85-C85 -> 0.24916667 | AA85: =Z85-Z84 -> -0.01 | AB85: 22.75 | AC85: 6.9078947 | AD85: =M85-N85 -> 0.017972829
A86: 44197 | B86: -0.0016597288 | C86: -0.275 | D86: -0.0066666667 | E86: 0.030833333 | F86: 0.073333333 | G86: =0.3657*E86+(1-0.3657)*D86 -> 0.0070470833 | H86: -1.6407305 | I86: 0.07312729 | J86: 3793.7484 | K86: =-1+J86/J85 -> 0.026638745 | L86: =L85*2/3+L88/3 -> 105.48667 | M86: =L86/J86 -> 0.027805393 | N86: 0.0075 | O86: -0.72114035 | P86: =F86-D86 -> 0.08 | Q86: =2*E86-F86-D86 -> -0.005 | R86: 0.0041166667 | S86: =R86-N86 -> -0.0033833333 | T86: =D86-B86 -> -0.0050069379 | U86: =P86-P85 -> 0.01 | V86: =Q86-Q85 -> 0.0066666667 | W86: =H86-G86 -> -1.6477776 | X86: =I86-H86 -> 1.7138578 | Y86: =K86-I86 -> -0.046488544 | Z86: =D86-C86 -> 0.26833333 | AA86: =Z86-Z85 -> 0.019166667 | AB86: 33.09 | AC86: 45.450549 | AD86: =M86-N86 -> 0.020305393
A87: 44228 | B87: 0.018358151 | C87: -0.26416667 | D87: 0.015 | E87: 0.074166667 | F87: 0.115 | G87: =0.3657*E87+(1-0.3657)*D87 -> 0.03663725 | H87: -3.4432121 | I87: 0.10199835 | J87: 3883.4321 | K87: =-1+J87/J86 -> 0.023639861 | L87: =L85/3+L88*2/3 -> 116.84333 | M87: =L87/J87 -> 0.030087647 | N87: 0.0066666667 | O87: -0.028872892 | P87: =F87-D87 -> 0.1 | Q87: =2*E87-F87-D87 -> 0.018333333 | R87: 0.00405 | S87: =R87-N87 -> -0.0026166667 | T87: =D87-B87 -> -0.003358151 | U87: =P87-P86 -> 0.02 | V87: =Q87-Q86 -> 0.023333333 | W87: =H87-G87 -> -3.4798494 | X87: =I87-H87 -> 3.5452105 | Y87: =K87-I87 -> -0.078358489 | Z87: =D87-C87 -> 0.27916667 | AA87: =Z87-Z86 -> 0.010833333 | AB87: 27.95 | AC87: -15.533394 | AD87: =M87-N87 -> 0.02342098
A88: 44256 | B88: 0.019283546 | C88: -0.28583333 | D88: 0.013333333 | E88: 0.0775 | F88: 0.1175 | G88: =0.3657*E88+(1-0.3657)*D88 -> 0.036799083 | H88: 0.053989228 | I88: 0.69957763 | J88: 3910.5083 | K88: =-1+J88/J87 -> 0.0069722232 | L88: 128.2 | M88: =L88/J88 -> 0.032783462 | N88: 0.0058333333 | O88: 2.1554149 | P88: =F88-D88 -> 0.10416667 | Q88: =2*E88-F88-D88 -> 0.024166667 | R88: 0.00405 | S88: =R88-N88 -> -0.0017833333 | T88: =D88-B88 -> -0.0059502125 | U88: =P88-P87 -> 0.0041666667 | V88: =Q88-Q87 -> 0.0058333333 | W88: =H88-G88 -> 0.017190145 | X88: =I88-H88 -> 0.64558841 | Y88: =K88-I88 -> -0.69260541 | Z88: =D88-C88 -> 0.29916667 | AA88: =Z88-Z87 -> 0.02 | AB88: 19.4 | AC88: -32.096605 | AD88: =M88-N88 -> 0.026950129
A89: 44287 | B89: 0.022403503 | C89: -0.27166667 | D89: 0.014166667 | E89: 0.0775 | F89: 0.1125 | G89: =0.3657*E89+(1-0.3657)*D89 -> 0.037327667 | H89: 0.41775962 | I89: 0.62538663 | J89: 4141.1762 | K89: =-1+J89/J88 -> 0.058986688 | L89: =L88*2/3+L91/3 -> 138.38667 | M89: =L89/J89 -> 0.033417237 | N89: 0.0058333333 | O89: 2.3109716 | P89: =F89-D89 -> 0.098333333 | Q89: =2*E89-F89-D89 -> 0.028333333 | R89: 0.00405 | S89: =R89-N89 -> -0.0017833333 | T89: =D89-B89 -> -0.0082368361 | U89: =P89-P88 -> -0.0058333333 | V89: =Q89-Q88 -> 0.0041666667 | W89: =H89-G89 -> 0.38043196 | X89: =I89-H89 -> 0.20762701 | Y89: =K89-I89 -> -0.56639995 | Z89: =D89-C89 -> 0.28583333 | AA89: =Z89-Z88 -> -0.013333333 | AB89: 18.61 | AC89: 3.908431 | AD89: =M89-N89 -> 0.027583904
A90: 44317 | B90: 0.020841211 | C90: -0.29416667 | D90: 0.011666667 | E90: 0.074166667 | F90: 0.11083333 | G90: =0.3657*E90+(1-0.3657)*D90 -> 0.034522917 | H90: 0.34453723 | I90: 0.39501046 | J90: 4167.8495 | K90: =-1+J90/J89 -> 0.0064409985 | L90: =L88/3+L91*2/3 -> 148.57333 | M90: =L90/J90 -> 0.03564748 | N90: 0.005 | O90: 0.2517622 | P90: =F90-D90 -> 0.099166667 | Q90: =2*E90-F90-D90 -> 0.025833333 | R90: 0.004125 | S90: =R90-N90 -> -0.000875 | T90: =D90-B90 -> -0.0091745448 | U90: =P90-P89 -> 0.00083333333 | V90: =Q90-Q89 -> -0.0025 | W90: =H90-G90 -> 0.31001432 | X90: =I90-H90 -> 0.050473223 | Y90: =K90-I90 -> -0.38856946 | Z90: =D90-C90 -> 0.30583333 | AA90: =Z90-Z89 -> 0.02 | AB90: 16.76 | AC90: -8.4653195 | AD90: =M90-N90 -> 0.03064748
A91: 44348 | B91: 0.025316625 | C91: -0.26333333 | D91: 0.014166667 | E91: 0.068333333 | F91: 0.105 | G91: =0.3657*E91+(1-0.3657)*D91 -> 0.033975417 | H91: 0.88899758 | I91: 0.77723012 | J91: 4238.4895 | K91: =-1+J91/J90 -> 0.016948799 | L91: 158.76 | M91: =L91/J91 -> 0.03745674 | N91: 0.0066666667 | O91: 1.193512 | P91: =F91-D91 -> 0.090833333 | Q91: =2*E91-F91-D91 -> 0.0175 | R91: 0.00415 | S91: =R91-N91 -> -0.0025166667 | T91: =D91-B91 -> -0.011149958 | U91: =P91-P90 -> -0.0083333333 | V91: =Q91-Q90 -> -0.0083333333 | W91: =H91-G91 -> 0.85502217 | X91: =I91-H91 -> -0.11176746 | Y91: =K91-I91 -> -0.76028132 | Z91: =D91-C91 -> 0.2775 | AA91: =Z91-Z90 -> -0.028333333 | AB91: 15.83 | AC91: -12.250554 | AD91: =M91-N91 -> 0.030790073
A92: 44378 | B92: 0.025540679 | C92: -0.28333333 | D92: 0.011666667 | E92: 0.054166667 | F92: 0.085 | G92: =0.3657*E92+(1-0.3657)*D92 -> 0.027208917 | H92: 1.6404399 | I92: 0.42632494 | J92: 4363.7129 | K92: =-1+J92/J91 -> 0.029544325 | L92: =L91*2/3+L94/3 -> 164.31667 | M92: =L92/J92 -> 0.037655243 | N92: 0.0083333333 | O92: 1.0885623 | P92: =F92-D92 -> 0.073333333 | Q92: =2*E92-F92-D92 -> 0.011666667 | R92: 0.0042166667 | S92: =R92-N92 -> -0.0041166667 | T92: =D92-B92 -> -0.013874012 | U92: =P92-P91 -> -0.0175 | V92: =Q92-Q91 -> -0.0058333333 | W92: =H92-G92 -> 1.613231 | X92: =I92-H92 -> -1.214115 | Y92: =K92-I92 -> -0.39678062 | Z92: =D92-C92 -> 0.295 | AA92: =Z92-Z91 -> 0.0175 | AB92: 18.24 | AC92: 21.035169 | AD92: =M92-N92 -> 0.029321909
A93: 44409 | B93: 0.029828797 | C93: -0.285 | D93: 0.0175 | E93: 0.059166667 | F93: 0.091666667 | G93: =0.3657*E93+(1-0.3657)*D93 -> 0.0327375 | H93: -0.19596708 | I93: 0.4120331 | J93: 4454.2064 | K93: =-1+J93/J92 -> 0.020737732 | L93: =L91/3+L94*2/3 -> 169.87333 | M93: =L93/J93 -> 0.038137733 | N93: 0.0075 | O93: 1.4799167 | P93: =F93-D93 -> 0.074166667 | Q93: =2*E93-F93-D93 -> 0.0091666667 | R93: 0.0042 | S93: =R93-N93 -> -0.0033 | T93: =D93-B93 -> -0.012328797 | U93: =P93-P92 -> 0.00083333333 | V93: =Q93-Q92 -> -0.0025 | W93: =H93-G93 -> -0.22870458 | X93: =I93-H93 -> 0.60800018 | Y93: =K93-I93 -> -0.39129536 | Z93: =D93-C93 -> 0.3025 | AA93: =Z93-Z92 -> 0.0075 | AB93: 16.48 | AC93: -8.2915971 | AD93: =M93-N93 -> 0.030637733
A94: 44440 | B94: 0.051950352 | C94: -0.31166667 | D94: 0.036666667 | E94: 0.086666667 | F94: 0.11916667 | G94: =0.3657*E94+(1-0.3657)*D94 -> 0.054951667 | H94: -2.7538144 | I94: -0.3657987 | J94: 4445.5433 | K94: =-1+J94/J93 -> -0.00194491 | L94: 175.43 | M94: =L94/J94 -> 0.039461993 | N94: 0.0066666667 | O94: -1.3312319 | P94: =F94-D94 -> 0.0825 | Q94: =2*E94-F94-D94 -> 0.0175 | R94: 0.0041666667 | S94: =R94-N94 -> -0.0025 | T94: =D94-B94 -> -0.015283685 | U94: =P94-P93 -> 0.0083333333 | V94: =Q94-Q93 -> 0.0083333333 | W94: =H94-G94 -> -2.8087661 | X94: =I94-H94 -> 2.3880157 | Y94: =K94-I94 -> 0.36385379 | Z94: =D94-C94 -> 0.34833333 | AA94: =Z94-Z93 -> 0.045833333 | AB94: 23.14 | AC94: 41.011578 | AD94: =M94-N94 -> 0.032795326
A95: 44470 | B95: 0.090511268 | C95: -0.31333333 | D95: 0.059166667 | E95: 0.086666667 | F95: 0.099166667 | G95: =0.3657*E95+(1-0.3657)*D95 -> 0.069223417 | H95: 0.76644488 | I95: -0.1933388 | J95: 4460.7071 | K95: =-1+J95/J94 -> 0.0034110138 | L95: =L94*2/3+L97/3 -> 182.91 | M95: =L95/J95 -> 0.041004709 | N95: 0.0066666667 | O95: 1.7130121 | P95: =F95-D95 -> 0.04 | Q95: =2*E95-F95-D95 -> 0.015 | R95: 0.0041833333 | S95: =R95-N95 -> -0.0024833333 | T95: =D95-B95 -> -0.031344601 | U95: =P95-P94 -> -0.0425 | V95: =Q95-Q94 -> -0.0025 | W95: =H95-G95 -> 0.69722146 | X95: =I95-H95 -> -0.95978368 | Y95: =K95-I95 -> 0.19674982 | Z95: =D95-C95 -> 0.3725 | AA95: =Z95-Z94 -> 0.024166667 | AB95: 16.26 | AC95: -29.181185 | AD95: =M95-N95 -> 0.034338043
A96: 44501 | B96: 0.080248899 | C96: -0.35833333 | D96: 0.041666667 | E96: 0.068333333 | F96: 0.083333333 | G96: =0.3657*E96+(1-0.3657)*D96 -> 0.051418667 | H96: 1.0468942 | I96: -1.1502864 | J96: 4667.3867 | K96: =-1+J96/J95 -> 0.046333354 | L96: =L94/3+L97*2/3 -> 190.39 | M96: =L96/J96 -> 0.040791564 | N96: 0.0066666667 | O96: 0.34169514 | P96: =F96-D96 -> 0.041666667 | Q96: =2*E96-F96-D96 -> 0.011666667 | R96: 0.0039 | S96: =R96-N96 -> -0.0027666667 | T96: =D96-B96 -> -0.038582232 | U96: =P96-P95 -> 0.0016666667 | V96: =Q96-Q95 -> -0.0033333333 | W96: =H96-G96 -> 0.99547551 | X96: =I96-H96 -> -2.1971806 | Y96: =K96-I96 -> 1.1966198 | Z96: =D96-C96 -> 0.4 | AA96: =Z96-Z95 -> 0.0275 | AB96: 27.19 | AC96: 69.619464 | AD96: =M96-N96 -> 0.034124897
A97: 44531 | B97: 0.088834034 | C97: -0.2975 | D97: 0.0575 | E97: 0.081666667 | F97: 0.10166667 | G97: =0.3657*E97+(1-0.3657)*D97 -> 0.06633775 | H97: -1.0572013 | I97: 1.8147767 | J97: 4674.7727 | K97: =-1+J97/J96 -> 0.0015824831 | L97: 197.87 | M97: =L97/J97 -> 0.042327191 | N97: 0.0066666667 | O97: 1.3592931 | P97: =F97-D97 -> 0.044166667 | Q97: =2*E97-F97-D97 -> 0.0041666667 | R97: 0.0095083333 | S97: =R97-N97 -> 0.0028416667 | T97: =D97-B97 -> -0.031334034 | U97: =P97-P96 -> 0.0025 | V97: =Q97-Q96 -> -0.0075 | W97: =H97-G97 -> -1.123539 | X97: =I97-H97 -> 2.871978 | Y97: =K97-I97 -> -1.8131942 | Z97: =D97-C97 -> 0.355 | AA97: =Z97-Z96 -> -0.045 | AB97: 17.22 | AC97: -43.853929 | AD97: =M97-N97 -> 0.035660525
A98: 44562 | B98: 0.11624732 | C98: -0.29833333 | D98: 0.086666667 | E98: 0.11 | F98: 0.1275 | G98: =0.3657*E98+(1-0.3657)*D98 -> 0.095199667 | H98: -3.9390798 | I98: -2.3735666 | J98: 4573.8155 | K98: =-1+J98/J97 -> -0.021596179 | L98: =L97*2/3+L100/3 -> 197.88333 | M98: =L98/J98 -> 0.043264389 | N98: 0.0066666667 | O98: -2.2568119 | P98: =F98-D98 -> 0.040833333 | Q98: =2*E98-F98-D98 -> 0.0058333333 | R98: 0.016316667 | S98: =R98-N98 -> 0.00965 | T98: =D98-B98 -> -0.029580657 | U98: =P98-P97 -> -0.0033333333 | V98: =Q98-Q97 -> 0.0016666667 | W98: =H98-G98 -> -4.0342795 | X98: =I98-H98 -> 1.5655132 | Y98: =K98-I98 -> 2.3519704 | Z98: =D98-C98 -> 0.385 | AA98: =Z98-Z97 -> 0.03 | AB98: 24.83 | AC98: 49.578313 | AD98: =M98-N98 -> 0.036597722
A99: 44593 | B99: 0.13228576 | C99: -0.33 | D99: 0.088333333 | E99: 0.11916667 | F99: 0.14083333 | G99: =0.3657*E99+(1-0.3657)*D99 -> 0.099609083 | H99: -3.0655598 | I99: -1.1662747 | J99: 4435.9805 | K99: =-1+J99/J98 -> -0.030135665 | L99: =L97/3+L100*2/3 -> 197.89667 | M99: =L99/J99 -> 0.044611708 | N99: 0.0066666667 | O99: -1.107221 | P99: =F99-D99 -> 0.0525 | Q99: =2*E99-F99-D99 -> 0.0091666667 | R99: 0.034991667 | S99: =R99-N99 -> 0.028325 | T99: =D99-B99 -> -0.043952425 | U99: =P99-P98 -> 0.011666667 | V99: =Q99-Q98 -> 0.0033333333 | W99: =H99-G99 -> -3.1651689 | X99: =I99-H99 -> 1.8992851 | Y99: =K99-I99 -> 1.136139 | Z99: =D99-C99 -> 0.41833333 | AA99: =Z99-Z98 -> 0.033333333 | AB99: 30.15 | AC99: 21.425695 | AD99: =M99-N99 -> 0.037945041
A100: 44621 | B100: 0.16608815 | C100: -0.32833333 | D100: 0.1175 | E100: 0.13583333 | F100: 0.155 | G100: =0.3657*E100+(1-0.3657)*D100 -> 0.1242045 | H100: 0.25747217 | I100: -0.63178803 | J100: 4391.2652 | K100: =-1+J100/J99 -> -0.010080141 | L100: 197.91 | M100: =L100/J100 -> 0.045069015 | N100: 0.016666667 | O100: 1.9965489 | P100: =F100-D100 -> 0.0375 | Q100: =2*E100-F100-D100 -> -0.00083333333 | R100: 0.046858333 | S100: =R100-N100 -> 0.030191667 | T100: =D100-B100 -> -0.048588149 | U100: =P100-P99 -> -0.015 | V100: =Q100-Q99 -> -0.01 | W100: =H100-G100 -> 0.13326767 | X100: =I100-H100 -> -0.8892602 | Y100: =K100-I100 -> 0.62170789 | Z100: =D100-C100 -> 0.44583333 | AA100: =Z100-Z99 -> 0.0275 | AB100: 20.56 | AC100: -35.709819 | AD100: =M100-N100 -> 0.028402349
...

Sheet Data for CSV Export
A1: date | B1: asset_returns | C1: SONIA | D1: SONIA_EFFR_spread | E1: slope | F1: slope_change | G1: butterfly | H1: butterfly_change | I1: swap_spread | J1: IG_gilt_spread | K1: HY_IG_spread | L1: inflation | M1: inflation_change | N1: S&P_500_HY_spread | O1: S&P_500_ERP | P1: VIX | Q1: VIX_change
A2: {=Data!A2:A145} -> 41426 | B2: {=Data!O2:O145} -> -3.1231512 | C2: {=Data!R2:R145} -> 0.035433333 | D2: {=Data!S2:S145} -> 0.027933333 | E2: {=Data!P2:P145} -> 0.23333333 | F2: {=Data!U2:U145} -> -0.00074009324 | G2: {=Data!Q2:Q145} -> 0.081666667 | H2: {=Data!V2:V145} -> -0.00046037296 | I2: {=Data!T2:T145} -> 0.0082496246 | J2: {=Data!W2:W145} -> -5.1387194 | K2: {=Data!X2:X145} -> 5.9420041 | L2: {=Data!Z2:Z145} -> 0.1975 | M2: {=Data!AA2:AA145} -> 0.00036713287 | N2: {=Data!Y2:Y145} -> -0.91096438 | O2: {=Data!AD2:AD145} -> 0.048684634 | P2: {=Data!AB2:AB145} -> 16.86 | Q2: {=Data!AC2:AC145} -> 3.5626536
A3: 41456 | B3: 3.4388142 | C3: 0.035841667 | D3: 0.028341667 | E3: 0.245 | F3: 0.011666667 | G3: 0.081666667 | H3: 0 | I3: 0.0051715084 | J3: 2.3484491 | K3: -0.029334478 | L3: 0.2175 | M3: 0.02 | N3: -2.3980136 | O3: 0.047687334 | P3: 13.45 | Q3: -16.975309
A4: 41487 | B4: -1.8423177 | C4: 0.035583333 | D4: 0.028916667 | E4: 0.23416667 | F4: -0.010833333 | G4: 0.099166667 | H4: 0.0175 | I4: 0.0048092386 | J4: -0.92319479 | K4: 0.04392035 | L4: 0.2275 | M4: 0.01 | N4: 0.75000275 | O4: 0.049156672 | P4: 17.01 | Q4: 43.665541
A5: 41518 | B5: 0.76476526 | C5: 0.035825 | D5: 0.029158333 | E5: 0.22333333 | F5: -0.010833333 | G5: 0.093333333 | H5: -0.0058333333 | I5: 0.0038193557 | J5: 0.82434768 | K5: 0.2932183 | L5: 0.22833333 | M5: 0.00083333333 | N5: -1.2369081 | O5: 0.049267234 | P5: 16.6 | Q5: -0.060204696
A6: 41548 | B6: 2.8438546 | C6: 0.035941667 | D6: 0.028441667 | E6: 0.22166667 | F6: -0.0016666667 | G6: 0.09 | H6: -0.0033333333 | I6: 0.004928854 | J6: 2.0252116 | K6: 0.34411937 | L6: 0.23583333 | M6: 0.0075 | N6: -2.4760095 | O6: 0.048495147 | P6: 13.75 | Q6: -17.86141
A7: 41579 | B7: -0.40587404 | C7: 0.035833333 | D7: 0.029166667 | E7: 0.22916667 | F7: 0.0075 | G7: 0.10083333 | H7: 0.010833333 | I7: 0.007761623 | J7: -1.4083022 | K7: 1.3116082 | L7: 0.22833333 | M7: -0.0075 | N7: -0.0017227431 | O7: 0.048424145 | P7: 13.7 | Q7: 3.1626506
A8: 41609 | B8: 0.3946379 | C8: 0.035125 | D8: 0.027625 | E8: 0.2125 | F8: -0.016666667 | G8: 0.1175 | H8: 0.016666667 | I8: 0.0037650094 | J8: -0.8953169 | K8: 1.4775488 | L8: 0.24 | M8: 0.011666667 | N8: -0.72731482 | O8: 0.047927098 | P8: 13.72 | Q8: -5.7044674
A9: 41640 | B9: -0.84486748 | C9: 0.035725 | D9: 0.029891667 | E9: 0.20833333 | F9: -0.0041666667 | G9: 0.088333333 | H9: -0.029166667 | I9: 0.0017781225 | J9: 2.0846292 | K9: -1.698193 | L9: 0.22416667 | M9: -0.015833333 | N9: -0.52011652 | O9: 0.049269208 | P9: 18.41 | Q9: 33.793605
A10: 41671 | B10: 2.1320616 | C10: 0.034975 | D10: 0.029141667 | E10: 0.20666667 | F10: -0.0016666667 | G10: 0.091666667 | H10: 0.0033333333 | I10: -0.00016277218 | J10: 0.18815829 | K10: 1.5916814 | L10: 0.23333333 | M10: 0.0091666667 | N10: -1.9264759 | O10: 0.049549781 | P10: 14 | Q10: -23.954373
A11: 41699 | B11: -0.4241401 | C11: 0.034658333 | D11: 0.027991667 | E11: 0.19666667 | F11: -0.01 | G11: 0.083333333 | H11: -0.0083333333 | I11: 0.00095266584 | J11: -0.30403985 | K11: 0.17233654 | L11: 0.2375 | M11: 0.0041666667 | N11: 0.0069187077 | O11: 0.047451347 | P11: 13.88 | Q11: -1.5602837
A12: 41730 | B12: 0.74520035 | C12: 0.035166667 | D12: 0.027666667 | E12: 0.19166667 | F12: -0.005 | G12: 0.076666667 | H12: -0.0066666667 | I12: -0.00053543916 | J12: 1.2224064 | K12: -0.72031035 | L12: 0.245 | M12: 0.0075 | N12: -0.65076373 | O12: 0.047002412 | P12: 13.41 | Q12: 2.4446142
A13: 41760 | B13: 1.3893836 | C13: 0.035275 | D13: 0.027775 | E13: 0.18583333 | F13: -0.0058333333 | G13: 0.0675 | H13: -0.0091666667 | I13: -0.0020155552 | J13: 1.1188107 | K13: -0.73488673 | L13: 0.23333333 | M13: -0.011666667 | N13: -0.51489555 | O13: 0.046667086 | P13: 11.4 | Q13: -11.696359
A14: 41791 | B14: -0.15960421 | C14: 0.035425 | D14: 0.027091667 | E14: 0.16916667 | F14: -0.016666667 | G14: 0.0625 | H14: -0.005 | I14: -0.0021056525 | J14: -0.39386739 | K14: 1.1129799 | L14: 0.23333333 | M14: 0 | N14: -0.84947435 | O14: 0.044627752 | P14: 11.57 | Q14: -2.5273799
... A145: 45992 | B145: 0.64991632 | C145: 0.32324167 | D145: 0.013241667 | E145: 0.1275 | F145: -0.0025 | G145: 0.015833333 | H145: 0.0025 | I145: 0.017714206 | J145: 0.22777557 | K145: 0.045576251 | L145: 0.25 | M145: -0.0091666667 | N145: -0.59209124 | O145: -0.27306595 | P145: 14.95 | Q145: -7.0273632

Sheet Factor Graphs

Sheet Correlations
B1: slope | C1: butterfly | D1: SONIA | E1: SONIA_EFFR | F1: swap_spread | G1: slope_change | H1: butterfly_change | I1: IG_gilt | J1: HY_IG | K1: S&P_500_HY | L1: inflation | M1: inflation_change | N1: VIX | O1: VIX_change | P1: S&P_500_ERP
A2: slope | B2: 1 | C2: {=TRANSPOSE(B3:B16)} -> 0.88765444 | D2: -0.42088749 | E2: 0.39648998 | F2: 0.59008431 | G2: 0.076139492 | H2: 0.0067948388 | I2: 0.11856944 | J2: -0.043149024 | K2: -0.084023864 | L2: -0.57446258 | M2: 0.01185625 | N2: -0.32924267 | O2: -0.00028365185 | P2: 0.52629534
A3: butterfly | B3: 0.88765444 | C3: 1 | D3: {=TRANSPOSE(C4:C16)} -> -0.58977738 | E3: 0.3821994 | F3: 0.36547352 | G3: -0.021590024 | H3: 0.089079202 | I3: -0.0077315377 | J3: 0.027908517 | K3: 0.0055626168 | L3: -0.40386373 | M3: 0.0047999559 | N3: -0.22136101 | O3: 0.057750646 | P3: 0.68689314
A4: SONIA | B4: -0.42088749 | C4: -0.58977738 | D4: 1 | E4: {=TRANSPOSE(D5:D16)} -> 0.0030457154 | F4: -0.041698491 | G4: 0.12824121 | H4: 0.074361543 | I4: -0.00045154313 | J4: 0.03363418 | K4: -0.092001156 | L4: 0.34826079 | M4: -0.066594349 | N4: -0.12229129 | O4: -0.13237294 | P4: -0.96190474
A5: SONIA_EFFR | B5: 0.39648998 | C5: 0.3821994 | D5: 0.0030457154 | E5: 1 | F5: {=TRANSPOSE(E6:E16)} -> 0.338674 | G5: 0.070058823 | H5: 0.10335938 | I5: 0.045050065 | J5: -0.0073004133 | K5: -0.054346173 | L5: -0.093086024 | M5: 0.068835111 | N5: 0.062283554 | O5: -0.00016740123 | P5: 0.26771107
A6: swap_spread | B6: 0.59008431 | C6: 0.36547352 | D6: -0.041698491 | E6: 0.338674 | F6: 1 | G6: {=TRANSPOSE(F7:F16)} -> 0.03636016 | H6: 0.10724011 | I6: 0.16740175 | J6: -0.076251268 | K6: -0.1197923 | L6: -0.5138289 | M6: 0.089093567 | N6: -0.20565518 | O6: -0.02566677 | P6: 0.1245407
A7: slope_change | B7: 0.076139492 | C7: -0.021590024 | D7: 0.12824121 | E7: 0.070058823 | F7: 0.03636016 | G7: 1 | H7: {=TRANSPOSE(G8:G16)} -> 0.35213338 | I7: 0.083767808 | J7: -0.017240978 | K7: -0.09359429 | L7: 0.0017634481 | M7: -0.12403777 | N7: 0.071774903 | O7: -0.0078739406 | P7: -0.10790789
A8: butterfly_change | B8: 0.0067948388 | C8: 0.089079202 | D8: 0.074361543 | E8: 0.10335938 | F8: 0.10724011 | G8: 0.35213338 | H8: 1 | I8: {=TRANSPOSE(H9:H16)} -> -0.38753107 | J8: 0.39119362 | K8: 0.080504394 | L8: 0.075107542 | M8: 0.056238698 | N8: 0.10334057 | O8: 0.08075058 | P8: -0.050038537
A9: IG_gilt | B9: 0.11856944 | C9: -0.0077315377 | D9: -0.00045154313 | E9: 0.045050065 | F9: 0.16740175 | G9: 0.083767808 | H9: -0.38753107 | I9: 1 | J9: {=TRANSPOSE(I10:I16)} -> -0.60714343 | K9: -0.61796775 | L9: -0.27183892 | M9: -0.12229891 | N9: -0.28397382 | O9: -0.29446414 | P9: 0.011111068
A10: HY_IG | B10: -0.043149024 | C10: 0.027908517 | D10: 0.03363418 | E10: -0.0073004133 | F10: -0.076251268 | G10: -0.017240978 | H10: 0.39119362 | I10: -0.60714343 | J10: 1 | K10: {=TRANSPOSE(J11:J16)} -> -0.24735776 | L10: 0.19477554 | M10: 0.24325704 | N10: -0.082519843 | O10: -0.17278794 | P10: -0.036659792
A11: S&P_500_HY | B11: -0.084023864 | C11: 0.0055626168 | D11: -0.092001156 | E11: -0.054346173 | F11: -0.1197923 | G11: -0.09359429 | H11: 0.080504394 | I11: -0.61796775 | J11: -0.24735776 | K11: 1 | L11: {=TRANSPOSE(K12:K16)} -> 0.11807155 | M11: -0.079919181 | N11: 0.43386126 | O11: 0.5370128 | P11: 0.077368666
A12: inflation | B12: -0.57446258 | C12: -0.40386373 | D12: 0.34826079 | E12: -0.093086024 | F12: -0.5138289 | G12: 0.0017634481 | H12: 0.075107542 | I12: -0.27183892 | J12: 0.19477554 | K12: 0.11807155 | L12: 1 | M12: {=TRANSPOSE(L13:L16)} -> 0.18640677 | N12: 0.20575498 | O12: -0.008406068 | P12: -0.36589067
A13: inflation_change | B13: 0.01185625 | C13: 0.0047999559 | D13: -0.066594349 | E13: 0.068835111 | F13: 0.089093567 | G13: -0.12403777 | H13: 0.056238698 | I13: -0.12229891 | J13: 0.24325704 | K13: -0.079919181 | L13: 0.18640677 | M13: 1 | N13: {=TRANSPOSE(M14:M16)} -> -0.055902789 | O13: 0.015662513 | P13: 0.078080711
A14: VIX | B14: -0.32924267 | C14: -0.22136101 | D14: -0.12229129 | E14: 0.062283554 | F14: -0.20565518 | G14: 0.071774903 | H14: 0.10334057 | I14: -0.28397382 | J14: -0.082519843 | K14: 0.43386126 | L14: 0.20575498 | M14: -0.055902789 | N14: 1 | O14: {=TRANSPOSE(N15:N16)} -> 0.47112813 | P14: 0.12380706
A15: VIX_change | B15: -0.00028365185 | C15: 0.057750646 | D15: -0.13237294 | E15: -0.00016740123 | F15: -0.02566677 | G15: -0.0078739406 | H15: 0.08075058 | I15: -0.29446414 | J15: -0.17278794 | K15: 0.5370128 | L15: -0.008406068 | M15: 0.015662513 | N15: 0.47112813 | O15: 1 | P15: =O16 -> 0.12804606
A16: S&P_500_ERP | B16: 0.52629534 | C16: 0.68689314 | D16: -0.96190474 | E16: 0.26771107 | F16: 0.1245407 | G16: -0.10790789 | H16: -0.050038537 | I16: 0.011111068 | J16: -0.036659792 | K16: 0.077368666 | L16: -0.36589067 | M16: 0.078080711 | N16: 0.12380706 | O16: 0.12804606 | P16: 1

Sheet Full
A1: SUMMARY OUTPUT
A3: Regression Statistics
A4: Multiple R | B4: 0.8252773
A5: R Square | B5: 0.68108262
A6: Adjusted R Square | B6: 0.66466775
A7: Standard Error | B7: 1.0820806
A8: Observations | B8: 144
A10: ANOVA
B11: df | C11: SS | D11: MS | E11: F | F11: Significance F
A12: Regression | B12: 7 | C12: 340.07893 | D12: 48.582705 | E12: 41.491819 | F12: 8.4670326e-31
A13: Residual | B13: 136 | C13: 159.24218 | D13: 1.1708984
A14: Total | B14: 143 | C14: 499.32112
B16: Coefficients | C16: Standard Error | D16: t Stat | E16: P-value | F16: Lower 95% | G16: Upper 95% | H16: Lower 95.0% | I16: Upper 95.0%
A17: Intercept | B17: 0.55203172 | C17: 0.47502652 | D17: 1.1621072 | E17: 0.24722726 | F17: -0.3873621 | G17: 1.4914255 | H17: -0.3873621 | I17: 1.4914255
A18: Average SONIA (%) | B18: 4.4063376 | C18: 2.3066898 | D18: 1.9102428 | E18: 0.058207099 | F18: -0.15528165 | G18: 8.9679568 | H18: -0.15528165 | I18: 8.9679568
A19: 3Y Gilt - 3Y OIS (%) | B19: 0.59779691 | C19: 6.5626442 | D19: 0.091090861 | E19: 0.92755442 | F19: -12.380231 | G19: 13.575825 | H19: -12.380231 | I19: 13.575825
A20: Slope (20Y-3Y) (%) | B20: -3.5214093 | C20: 4.6306672 | D20: -0.76045399 | E20: 0.44829964 | F20: -12.678835 | G20: 5.6360165 | H20: -12.678835 | I20: 5.6360165
A21: Butterfly (2x10Y-20Y-3Y) (%) | B21: 1.8813566 | C21: 7.054118 | D21: 0.26670331 | E21: 0.79010157 | F21: -12.06859 | G21: 15.831304 | H21: -12.06859 | I21: 15.831304
A22: IG Credit Spread (%) | B22: 0.80308412 | C22: 0.04911537 | D22: 16.350974 | E22: 6.5468673e-34 | F22: 0.70595549 | G22: 0.90021275 | H22: 0.70595549 | I22: 0.90021275
A23: HY-IG Spread (%) | B23: 0.47337406 | C23: 0.059477259 | D23: 7.9589083 | E23: 6.0869841e-13 | F23: 0.35575416 | G23: 0.59099395 | H23: 0.35575416 | I23: 0.59099395
A24: S&P 500 ERP GBP Hedged (%) | B24: 4.0352191 | C24: 2.4181279 | D24: 1.6687368 | E24: 0.09747012 | F24: -0.74677583 | G24: 8.817214 | H24: -0.74677583 | I24: 8.817214
A28: RESIDUAL OUTPUT | E28: PROBABILITY OUTPUT
A30: Observation | B30: Predicted Asset Returns (%) | C30: Residuals | E30: Percentile | F30: Asset Returns (%)
A31: 1 | B31: -1.0725037 | C31: -2.0506475 | E31: 0.34722222 | F31: -7.0047285
A32: 2 | B32: 2.0684974 | C32: 1.3703167 | E32: 1.0416667 | F32: -4.6868599
A33: 3 | B33: -0.44858435 | C33: -1.3937333 | E33: 1.7361111 | F33: -4.1526948
A34: 4 | B34: 1.1009437 | C34: -0.33617845 | E34: 2.4305556 | F34: -3.6875242
A35: 5 | B35: 2.0870933 | C35: 0.75676132 | E35: 3.125 | F35: -3.3442886
A36: 6 | B36: -0.21742261 | C36: -0.18845143 | E36: 3.8194444 | F36: -3.1231512
A37: 7 | B37: 0.3556298 | C37: 0.039008105 | E37: 4.5138889 | F37: -2.9682787
A38: 8 | B38: 1.2121348 | C38: -2.0570023 | E38: 5.2083333 | F38: -2.5680571
A39: 9 | B39: 1.2552577 | C39: 0.87680398 | E39: 5.9027778 | F39: -2.5280473
A40: 10 | B40: 0.19844007 | C40: -0.62258018 | E40: 6.5972222 | F40: -2.5046977
A41: 11 | B41: 1.0063524 | C41: -0.26115203 | E41: 7.2916667 | F41: -2.2568119
A42: 12 | B42: 0.9177914 | C42: 0.47159224 | E42: 7.9861111 | F42: -1.9001782
... A174: 144 | B174: 0.6703582 | C174: -0.020441881 | E174: 99.652778 | F174: 5.5867023

Sheet SONIA, Credit, ERP
A1: SUMMARY OUTPUT
A3: Regression Statistics
A4: Multiple R | B4: 0.82309951
A5: R Square | B5: 0.6774928
A6: Adjusted R Square | B6: 0.66821202
A7: Standard Error | B7: 1.0763469
A8: Observations | B8: 144
A10: ANOVA
B11: df | C11: SS | D11: MS | E11: F | F11: Significance F
A12: Regression | B12: 4 | C12: 338.28646 | D12: 84.571615 | E12: 72.999533 | F12: 3.3535557e-33
A13: Residual | B13: 139 | C13: 161.03465 | D13: 1.1585227
A14: Total | B14: 143 | C14: 499.32112
B16: Coefficients | C16: Standard Error | D16: t Stat | E16: P-value | F16: Lower 95% | G16: Upper 95% | H16: Lower 95.0% | I16: Upper 95.0%
A17: Intercept | B17: 0.20325207 | C17: 0.12636649 | D17: 1.6084333 | E17: 0.11000931 | F17: -0.04659694 | G17: 0.45310108 | H17: -0.04659694 | I17: 0.45310108
A18: Average SONIA (%) | B18: 3.4779845 | C18: 2.1114949 | D18: 1.6471669 | E18: 0.10178264 | F18: -0.69681618 | G18: 7.6527853 | H18: -0.69681618 | I18: 7.6527853
A19: IG Credit Spread (%) | B19: 0.79275462 | C19: 0.047520535 | D19: 16.682359 | E19: 5.4247509e-35 | F19: 0.69879808 | G19: 0.88671117 | H19: 0.69879808 | I19: 0.88671117
A20: HY-IG Spread (%) | B20: 0.46943391 | C20: 0.059000873 | D20: 7.9563893 | E20: 5.5926108e-13 | F20: 0.3527787 | G20: 0.58608913 | H20: 0.3527787 | I20: 0.58608913
A21: S&P 500 ERP GBP Hedged (%) | B21: 2.8510881 | C21: 2.0088892 | D21: 1.4192361 | E21: 0.15806879 | F21: -1.1208429 | G21: 6.8230192 | H21: -1.1208429 | I21: 6.8230192
A25: RESIDUAL OUTPUT | E25: PROBABILITY OUTPUT
A27: Observation | B27: Predicted Asset Returns (%) | C27: Residuals | E27: Percentile | F27: Asset Returns (%)
A28: 1 | B28: -0.81907249 | C28: -2.3040787 | E28: 0.34722222 | F28: -7.0047285
A29: 2 | B29: 2.3118429 | C29: 1.1269712 | E29: 1.0416667 | F29: -4.6868599
A30: 3 | B30: -0.24408888 | C30: -1.5982288 | E30: 1.7361111 | F30: -4.1526948
A31: 4 | B31: 1.2594681 | C31: -0.49470288 | E31: 2.4305556 | F31: -3.6875242
A32: 5 | B32: 2.2335577 | C32: 0.61029692 | E32: 3.125 | F32: -3.3442886
A33: 6 | B33: -0.034783334 | C33: -0.3710907 | E33: 3.8194444 | F33: -3.1231512
A34: 7 | B34: 0.44590558 | C34: -0.051267674 | E34: 4.5138889 | F34: -2.9682787
A35: 8 | B35: 1.3233839 | C35: -2.1682514 | E35: 5.2083333 | F35: -2.5680571
A36: 9 | B36: 1.3625179 | C36: 0.76954369 | E36: 5.9027778 | F36: -2.5280473
A37: 10 | B37: 0.29895281 | C37: -0.72309291 | E37: 6.5972222 | F37: -2.5046977
A38: 11 | B38: 1.0904995 | C38: -0.3452991 | E38: 7.2916667 | F38: -2.2568119
A39: 12 | B39: 1.0009515 | C39: 0.38843212 | E39: 7.9861111 | F39: -1.9001782
... A171: 144 | B171: 0.75091168 | C171: -0.10099536 | E171: 99.652778 | F171: 5.5867023

Sheet SONIA, Credit, ERP, Inflation
A1: SUMMARY OUTPUT
A3: Regression Statistics
A4: Multiple R | B4: 0.82890226
A5: R Square | B5: 0.68707895
A6: Adjusted R Square | B6: 0.67574123
A7: Standard Error | B7: 1.0640641
A8: Observations | B8: 144
A10: ANOVA
B11: df | C11: SS | D11: MS | E11: F | F11: Significance F
A12: Regression | B12: 5 | C12: 343.07303 | D12: 68.614606 | E12: 60.601162 | F12: 3.9000241e-33
A13: Residual | B13: 138 | C13: 156.24809 | D13: 1.1322325
A14: Total | B14: 143 | C14: 499.32112
B16: Coefficients | C16: Standard Error | D16: t Stat | E16: P-value | F16: Lower 95% | G16: Upper 95% | H16: Lower 95.0% | I16: Upper 95.0%
A17: Intercept | B17: -0.71713677 | C17: 0.46474297 | D17: -1.5430825 | E17: 0.12510081 | F17: -1.6360747 | G17: 0.20180116 | H17: -1.6360747 | I17: 0.20180116
A18: Average SONIA (%) | B18: 3.4971559 | C18: 2.0874203 | D18: 1.6753482 | E18: 0.096130399 | F18: -0.63030771 | G18: 7.6246196 | H18: -0.63030771 | I18: 7.6246196
A19: IG Credit Spread (%) | B19: 0.81421953 | C19: 0.048124234 | D19: 16.919117 | E19: 1.8216166e-35 | F19: 0.71906331 | G19: 0.90937575 | H19: 0.71906331 | I19: 0.90937575
A20: HY-IG Spread (%) | B20: 0.46622379 | C20: 0.058348474 | D20: 7.9903339 | E20: 4.7867554e-13 | F20: 0.35085114 | G20: 0.58159643 | H20: 0.35085114 | I20: 0.58159643
A21: S&P 500 ERP GBP Hedged (%) | B21: 3.3218485 | C21: 1.9991192 | D21: 1.661656 | E21: 0.098851818 | F21: -0.631017 | G21: 7.274714 | H21: -0.631017 | I21: 7.274714
A22: Inflation (3Y gilt - 3Y IL) (%) | B22: 3.6183958 | C22: 1.7598344 | D22: 2.0561001 | E22: 0.041657537 | F22: 0.13866889 | G22: 7.0981226 | H22: 0.13866889 | I22: 7.0981226
A26: RESIDUAL OUTPUT | E26: PROBABILITY OUTPUT
A28: Observation | B28: Predicted Asset Returns (%) | C28: Residuals | E28: Percentile | F28: Asset Returns (%)
A29: 1 | B29: -1.1306068 | C29: -1.9925444 | E29: 0.34722222 | F29: -7.0047285
A30: 2 | B30: 2.252095 | C30: 1.1867191 | E30: 1.0416667 | F30: -4.6868599
A31: 3 | B31: -0.33742676 | C31: -1.5048909 | E31: 1.7361111 | F31: -4.1526948
A32: 4 | B32: 1.2059128 | C32: -0.44114756 | E32: 2.4305556 | F32: -3.6875242
A33: 5 | B33: 2.2323922 | C33: 0.61146246 | E33: 3.125 | F33: -3.3442886
A34: 6 | B34: -0.13992816 | C34: -0.26594588 | E34: 3.8194444 | F34: -3.1231512
A35: 7 | B35: 0.39320629 | C35: 0.0014316166 | E35: 4.5138889 | F35: -2.9682787
A36: 8 | B36: 1.2881955 | C36: -2.133063 | E36: 5.2083333 | F36: -2.5680571
A37: 9 | B37: 1.3093474 | C37: 0.82271429 | E37: 5.9027778 | F37: -2.5280473
A38: 10 | B38: 0.25385622 | C38: -0.67799632 | E38: 6.5972222 | F38: -2.5046977
A39: 11 | B39: 1.1079698 | C39: -0.36276942 | E39: 7.2916667 | F39: -2.2568119
A40: 12 | B40: 0.97387455 | C40: 0.41550908 | E40: 7.9861111 | F40: -1.9001782
... A172: 144 | B172: 0.61751303 | C172: 0.032403292 | E172: 99.652778 | F172: 5.5867023

Sheet Credit, ERP, Inflation
A1: SUMMARY OUTPUT
A3: Regression Statistics
A4: Multiple R | B4: 0.8250542
A5: R Square | B5: 0.68071443
A6: Adjusted R Square | B6: 0.67152635
A7: Standard Error | B7: 1.0709574
A8: Observations | B8: 144
A10: ANOVA
B11: df | C11: SS | D11: MS | E11: F | F11: Significance F
A12: Regression | B12: 4 | C12: 339.89509 | D12: 84.973772 | E12: 74.086738 | F12: 1.6768523e-33
A13: Residual | B13: 139 | C13: 159.42603 | D13: 1.1469498
A14: Total | B14: 143 | C14: 499.32112
B16: Coefficients | C16: Standard Error | D16: t Stat | E16: P-value | F16: Lower 95% | G16: Upper 95% | H16: Lower 95.0% | I16: Upper 95.0%
A17: Intercept | B17: -0.59942015 | C17: 0.46237682 | D17: -1.2963888 | E17: 0.19698973 | F17: -1.5136213 | G17: 0.314781 | H17: -1.5136213 | I17: 0.314781
A18: IG Credit Spread (%) | B18: 0.81749189 | C18: 0.048396084 | D18: 16.891695 | E18: 1.6924135e-35 | F18: 0.72180423 | G18: 0.91317955 | H18: 0.72180423 | I18: 0.91317955
A19: HY-IG Spread (%) | B19: 0.46829973 | C19: 0.058713227 | D19: 7.9760516 | E19: 5.0142596e-13 | F19: 0.35221324 | G19: 0.58438621 | H19: 0.35221324 | I19: 0.58438621
A20: S&P 500 ERP GBP Hedged (%) | B20: 0.11972347 | C20: 0.58974552 | D20: 0.2030087 | E20: 0.8394251 | F20: -1.0463082 | G20: 1.2857552 | H20: -1.0463082 | I20: 1.2857552
A21: Inflation (3Y gilt - 3Y IL) (%) | B21: 3.605226 | C21: 1.7712174 | D21: 2.0354508 | E21: 0.04370576 | F21: 0.10321436 | G21: 7.1072377 | H21: 0.10321436 | I21: 7.1072377
A25: RESIDUAL OUTPUT | F25: PROBABILITY OUTPUT
A27: Observation | B27: Predicted Asset Returns (%) | C27: Residuals | D27: Standard Residuals | F27: Percentile | G27: Asset Returns (%)
A28: 1 | B28: -1.2997818 | C28: -1.8233694 | D28: -1.7268836 | F28: 0.34722222 | G28: -7.0047285
A29: 2 | B29: 2.0965266 | C29: 1.3422876 | D29: 1.2712588 | F29: 1.0416667 | G29: -4.6868599
A30: 3 | B30: -0.50748238 | C30: -1.3348353 | D30: -1.2642009 | F30: 1.7361111 | G30: -4.1526948
A31: 4 | B31: 1.0408832 | C31: -0.2761179 | D31: -0.26150679 | F31: 2.4305556 | G31: -3.6875242
A32: 5 | B32: 2.0733634 | C32: 0.77049126 | D32: 0.72971979 | F32: 3.125 | G32: -3.3442886
A33: 6 | B33: -0.30747921 | C33: -0.098394832 | D33: -0.093188151 | F33: 3.8194444 | G33: -3.1231512
A34: 7 | B34: 0.23159351 | C34: 0.1630444 | D34: 0.1544167 | F34: 4.5138889 | G34: -2.9682787
A35: 8 | B35: 1.1235542 | C35: -1.9684216 | D35: -1.8642602 | F35: 5.2083333 | G35: -2.5680571
A36: 9 | B36: 1.1469334 | C36: 0.98512828 | D36: 0.93299903 | F36: 5.9027778 | G36: -2.5280473
A37: 10 | B37: 0.094657117 | C37: -0.51879722 | D37: -0.49134444 | F37: 6.5972222 | G37: -2.5046977
A38: 11 | B38: 0.95147372 | C38: -0.20627336 | D38: -0.19535816 | F38: 7.2916667 | G38: -2.2568119
A39: 12 | B39: 0.81785778 | C39: 0.57152586 | D39: 0.54128288 | F39: 7.9861111 | G39: -1.9001782
... A171: 144 | B171: 0.47674198 | C171: 0.17317434 | D171: 0.16401061 | F171: 99.652778 | G171: 5.5867023

Sheet SONIA, Credit, Inflation
A1: SUMMARY OUTPUT
A3: Regression Statistics
A4: Multiple R | B4: 0.82511698
A5: R Square | B5: 0.68081803
A6: Adjusted R Square | B6: 0.67163294
A7: Standard Error | B7: 1.0707837
A8: Observations | B8: 144
A10: ANOVA
B11: df | C11: SS | D11: MS | E11: F | F11: Significance F
A12: Regression | B12: 4 | C12: 339.94682 | D12: 84.986705 | E12: 74.122066 | F12: 1.639697e-33
A13: Residual | B13: 139 | C13: 159.3743 | D13: 1.1465777
A14: Total | B14: 143 | C14: 499.32112
B16: Coefficients | C16: Standard Error | D16: t Stat | E16: P-value | F16: Lower 95% | G16: Upper 95% | H16: Lower 95.0% | I16: Upper 95.0%
A17: Intercept | B17: -0.54832066 | C17: 0.45636629 | D17: -1.2014925 | E17: 0.23160338 | F17: -1.4506379 | G17: 0.3539966 | H17: -1.4506379 | I17: 0.3539966
A18: Average SONIA (%) | B18: 0.18091902 | C18: 0.61569468 | D18: 0.29384536 | E18: 0.76931438 | F18: -1.0364188 | G18: 1.3982568 | H18: -1.0364188 | I18: 1.3982568
A19: IG Credit Spread (%) | B19: 0.81511097 | C19: 0.048425127 | D19: 16.832397 | E19: 2.3527801e-35 | F19: 0.71936589 | G19: 0.91085606 | H19: 0.71936589 | I19: 0.91085606
A20: HY-IG Spread (%) | B20: 0.46748662 | C20: 0.058711961 | D20: 7.9623745 | E20: 5.4098829e-13 | F20: 0.35140264 | G20: 0.58357061 | H20: 0.35140264 | I20: 0.58357061
A21: Inflation (3Y gilt - 3Y IL) (%) | B21: 3.2834844 | C21: 1.7592946 | D21: 1.8663641 | E21: 0.064097449 | F21: -0.19495376 | G21: 6.7619226 | H21: -0.19495376 | I21: 6.7619226
A25: RESIDUAL OUTPUT | F25: PROBABILITY OUTPUT
A27: Observation | B27: Predicted Asset Returns (%) | C27: Residuals | D27: Standard Residuals | F27: Percentile | G27: Asset Returns (%)
A28: 1 | B28: -1.3042411 | C28: -1.8189101 | D28: -1.7229399 | F28: 0.34722222 | G28: -7.0047285
A29: 2 | B29: 2.0728548 | C29: 1.3659593 | D29: 1.2938879 | F29: 1.0416667 | G29: -4.6868599
A30: 3 | B30: -0.52686428 | C30: -1.3154534 | D30: -1.2460468 | F30: 1.7361111 | G30: -4.1526948
A31: 4 | B31: 1.0169002 | C31: -0.25213491 | D31: -0.23883164 | F31: 2.4305556 | G31: -3.6875242
A32: 5 | B32: 2.0441803 | C32: 0.7996743 | D32: 0.75748148 | F32: 3.125 | G32: -3.3442886
A33: 6 | B33: -0.32687206 | C33: -0.07900198 | D33: -0.074833638 | F33: 3.8194444 | G33: -3.1231512
A34: 7 | B34: 0.20702206 | C34: 0.18761584 | D34: 0.17771676 | F34: 4.5138889 | G34: -2.9682787
A35: 8 | B35: 1.099512 | C35: -1.9443795 | D35: -1.8417892 | F35: 5.2083333 | G35: -2.5680571
A36: 9 | B36: 1.121613 | C36: 1.0104487 | D36: 0.95713485 | F36: 5.9027778 | G36: -2.5280473
A37: 10 | B37: 0.070516047 | C37: -0.49465615 | D37: -0.46855685 | F37: 6.5972222 | G37: -2.5046977
A38: 11 | B38: 0.92215678 | C38: -0.17695642 | D38: -0.16761976 | F38: 7.2916667 | G38: -2.2568119
A39: 12 | B39: 0.79261274 | C39: 0.59677089 | D39: 0.56528376 | F39: 7.9861111 | G39: -1.9001782
... A171: 144 | B171: 0.53799966 | C171: 0.11191666 | D171: 0.10601166 | F171: 99.652778 | G171: 5.5867023

Sheet Credit, Inflation
A1: SUMMARY OUTPUT
A3: Regression Statistics
A4: Multiple R | B4: 0.82499683
A5: R Square | B5: 0.68061976
A6: Adjusted R Square | B6: 0.6737759
A7: Standard Error | B7: 1.0672839
A8: Observations | B8: 144
A10: ANOVA
B11: df | C11: SS | D11: MS | E11: F | F11: Significance F
A12: Regression | B12: 3 | C12: 339.84782 | D12: 113.28261 | E12: 99.449659 | F12: 1.5731236e-34
A13: Residual | B13: 140 | C13: 159.4733 | D13: 1.139095
A14: Total | B14: 143 | C14: 499.32112
B16: Coefficients | C16: Standard Error | D16: t Stat | E16: P-value | F16: Lower 95% | G16: Upper 95% | H16: Lower 95.0% | I16: Upper 95.0%
A17: Intercept | B17: -0.57542787 | C17: 0.44548455 | D17: -1.2916898 | E17: 0.19859296 | F17: -1.4561748 | G17: 0.30531902 | H17: -1.4561748 | I17: 0.30531902
A18: IG Credit Spread (%) | B18: 0.81656406 | C18: 0.048014531 | D18: 17.006603 | E18: 7.1351237e-36 | F18: 0.72163675 | G18: 0.91149137 | H18: 0.72163675 | I18: 0.91149137
A19: HY-IG Spread (%) | B19: 0.46800367 | C19: 0.058493781 | D19: 8.0009132 | E19: 4.2268069e-13 | F19: 0.35235832 | G19: 0.58364901 | H19: 0.35235832 | I19: 0.58364901
A20: Inflation (3Y gilt - 3Y IL) (%) | B20: 3.469962 | C20: 1.6354862 | D20: 2.12167 | E20: 0.035626877 | F20: 0.23651788 | G20: 6.7034062 | H20: 0.23651788 | I20: 6.7034062
A24: RESIDUAL OUTPUT | F24: PROBABILITY OUTPUT
A26: Observation | B26: Predicted Asset Returns (%) | C26: Residuals | D26: Standard Residuals | F26: Percentile | G26: Asset Returns (%)
A27: 1 | B27: -1.3053243 | C27: -1.817827 | D27: -1.7213793 | F27: 0.34722222 | G27: -7.0047285
A28: 2 | B28: 2.0832194 | C28: 1.3555948 | D28: 1.2836716 | F28: 1.0416667 | G28: -4.6868599
A29: 3 | B29: -0.51930431 | C29: -1.3230134 | D29: -1.2528188 | F29: 1.7361111 | G29: -4.1526948
A30: 4 | B30: 1.02724 | C30: -0.26247478 | D30: -0.24854877 | F30: 2.4305556 | G30: -3.6875242
A31: 5 | B31: 2.0576689 | C31: 0.78618568 | D31: 0.74447336 | F31: 3.125 | G31: -3.3442886
A32: 6 | B32: -0.31925137 | C32: -0.086622664 | D32: -0.082026762 | F32: 3.8194444 | G32: -3.1231512
A33: 7 | B33: 0.21777768 | C33: 0.17686023 | D33: 0.16747663 | F33: 4.5138889 | G33: -2.9682787
A34: 8 | B34: 1.1098947 | C34: -1.9547621 | D34: -1.8510492 | F34: 5.2083333 | G34: -2.5680571
A35: 9 | B35: 1.132786 | C35: 0.99927569 | D35: 0.94625754 | F35: 5.9027778 | G35: -2.5280473
A36: 10 | B36: 0.081074224 | C36: -0.50521433 | D36: -0.47840939 | F36: 6.5972222 | G36: -2.5046977
A37: 11 | B37: 0.93577809 | C37: -0.19057774 | D37: -0.18046634 | F37: 7.2916667 | G37: -2.2568119
A38: 12 | B38: 0.80388082 | C38: 0.58550282 | D38: 0.55443805 | F38: 7.9861111 | G38: -1.9001782
... A170: 144 | B170: 0.49938583 | C170: 0.1505305 | D170: 0.14254386 | F170: 99.652778 | G170: 5.5867023

Sheet Credit
A1: SUMMARY OUTPUT
A3: Regression Statistics
A4: Multiple R | B4: 0.8187494
A5: R Square | B5: 0.67035058
A6: Adjusted R Square | B6: 0.66567471
A7: Standard Error | B7: 1.0804547
A8: Observations | B8: 144
A10: ANOVA
B11: df | C11: SS | D11: MS | E11: F | F11: Significance F
A12: Regression | B12: 2 | C12: 334.7202 | D12: 167.3601 | E12: 143.36357 | F12: 1.0536292e-34
A13: Residual | B13: 141 | C13: 164.60091 | D13: 1.1673824
A14: Total | B14: 143 | C14: 499.32112
B16: Coefficients | C16: Standard Error | D16: t Stat | E16: P-value | F16: Lower 95% | G16: Upper 95% | H16: Lower 95.0% | I16: Upper 95.0%
A17: Intercept | B17: 0.35054132 | C17: 0.09044305 | D17: 3.8758238 | E17: 0.00016225787 | F17: 0.17174161 | G17: 0.52934103 | H17: 0.17174161 | I17: 0.52934103
A18: IG Credit Spread (%) | B18: 0.79648952 | C18: 0.047653953 | D18: 16.714028 | E18: 2.9410422e-35 | F18: 0.70228092 | G18: 0.89069812 | H18: 0.70228092 | I18: 0.89069812
A19: HY-IG Spread (%) | B19: 0.47282884 | C19: 0.059170848 | D19: 7.9909087 | E19: 4.3275242e-13 | F19: 0.35585213 | G19: 0.58980555 | H19: 0.35585213 | I19: 0.58980555
A23: RESIDUAL OUTPUT | F23: PROBABILITY OUTPUT
A25: Observation | B25: Predicted Asset Returns (%) | C25: Residuals | D25: Standard Residuals | F25: Percentile | G25: Asset Returns (%)
A26: 1 | B26: -0.93284394 | C26: -2.1903073 | D26: -2.0415355 | F26: 0.34722222 | G26: -7.0047285
A27: 2 | B27: 2.2071863 | C27: 1.2316279 | D27: 1.1479723 | F27: 1.0416667 | G27: -4.6868599
A28: 3 | B28: -0.36400685 | C28: -1.4783108 | D28: -1.3778999 | F28: 1.7361111 | G28: -4.1526948
A29: 4 | B29: 1.1457677 | C29: -0.38100242 | D29: -0.35512368 | F29: 2.4305556 | G29: -3.6875242
A30: 5 | B30: 2.1263107 | C30: 0.71754394 | D30: 0.66880637 | F30: 3.125 | G30: -3.3442886
A31: 6 | B31: -0.15099042 | C31: -0.25488362 | D31: -0.23757122 | F31: 3.8194444 | G31: -3.1231512
A32: 7 | B32: 0.33605849 | C32: 0.058579412 | D32: 0.054600536 | F32: 4.5138889 | G32: -2.9682787
A33: 8 | B33: 1.207972 | C33: -2.0528395 | D33: -1.9134049 | F33: 5.2083333 | G33: -2.5680571
A34: 9 | B34: 1.2530003 | C34: 0.87906135 | D34: 0.81935306 | F34: 5.9027778 | G34: -2.5280473
A35: 10 | B35: 0.18986245 | C35: -0.61400256 | D35: -0.5722978 | F35: 6.5972222 | G35: -2.5046977
A36: 11 | B36: 0.98359173 | C36: -0.23839137 | D36: -0.22219917 | F36: 7.2916667 | G36: -2.2568119
A37: 12 | B37: 0.89418665 | C37: 0.49519699 | D37: 0.46156184 | F37: 7.9861111 | G37: -1.9001782
... A169: 144 | B169: 0.55351194 | C169: 0.09640438 | D169: 0.089856327 | F169: 99.652778 | G169: 5.5867023

Sheet Credit, SP-HY
A1: SUMMARY OUTPUT
A3: Regression Statistics
A4: Multiple R | B4: 0.81889597
A5: R Square | B5: 0.67059061
A6: Adjusted R Square | B6: 0.66353183
A7: Standard Error | B7: 1.0839118
A8: Observations | B8: 144
A10: ANOVA
B11: df | C11: SS | D11: MS | E11: F | F11: Significance F
A12: Regression | B12: 3 | C12: 334.84005 | D12: 111.61335 | E12: 95.00102 | F12: 1.3600711e-33
A13: Residual | B13: 140 | C13: 164.48107 | D13: 1.1748648
A14: Total | B14: 143 | C14: 499.32112
B16: Coefficients | C16: Standard Error | D16: t Stat | E16: P-value | F16: Lower 95% | G16: Upper 95% | H16: Lower 95.0% | I16: Upper 95.0%
A17: Intercept | B17: 0.31831478 | C17: 0.13569539 | D17: 2.3458038 | E17: 0.020389637 | F17: 0.050037691 | G17: 0.58659186 | H17: 0.050037691 | I17: 0.58659186
A18: IG Credit Spread (%) | B18: 0.57043507 | C18: 0.70938192 | D18: 0.80412969 | E18: 0.42268541 | F18: -0.83205111 | G18: 1.9729212 | H18: -0.83205111 | I18: 1.9729212
A19: HY-IG Spread (%) | B19: 0.24534401 | C19: 0.714717 | D19: 0.34327435 | E19: 0.73190702 | F19: -1.1676899 | G19: 1.6583779 | H19: -1.1676899 | I19: 1.6583779
A20: S&P 500 - HY (%) | B20: -0.22900523 | C20: 0.717008 | D20: -0.31939006 | E20: 0.74990683 | F20: -1.6465686 | G20: 1.1885581 | H20: -1.6465686 | I20: 1.1885581
A24: RESIDUAL OUTPUT | F24: PROBABILITY OUTPUT
A26: Observation | B26: Predicted Asset Returns (%) | C26: Residuals | D26: Standard Residuals | F26: Percentile | G26: Asset Returns (%)
A27: 1 | B27: -0.94654027 | C27: -2.176611 | D27: -2.0295085 | F27: 0.34722222 | G27: -7.0047285
A28: 2 | B28: 2.1999131 | C28: 1.238901 | D28: 1.155172 | F28: 1.0416667 | G28: -4.6868599
A29: 3 | B29: -0.36928686 | C29: -1.4730308 | D29: -1.3734786 | F29: 1.7361111 | G29: -4.1526948
A30: 4 | B30: 1.1437494 | C30: -0.37898413 | D30: -0.35337115 | F30: 2.4305556 | G30: -3.6875242
A31: 5 | B31: 2.1250132 | C31: 0.7188414 | D31: 0.67025976 | F31: 3.125 | G31: -3.3442886
A32: 6 | B32: -0.16284044 | C32: -0.2430336 | D32: -0.2266086 | F32: 3.8194444 | G32: -3.1231512
A33: 7 | B33: 0.33666127 | C33: 0.057976633 | D33: 0.054058383 | F33: 4.5138889 | G33: -2.9682787
A34: 8 | B34: 1.2099283 | C34: -2.0547958 | D34: -1.915926 | F34: 5.2083333 | G34: -2.5680571
A35: 9 | B35: 1.2573294 | C35: 0.87473223 | D35: 0.81561497 | F35: 5.9027778 | G35: -2.5280473
A36: 10 | B36: 0.1855771 | C36: -0.6097172 | D36: -0.56851053 | F36: 6.5972222 | G36: -2.5046977
A37: 11 | B37: 0.98792274 | C37: -0.24272239 | D37: -0.22631842 | F37: 7.2916667 | G37: -2.2568119
A38: 12 | B38: 0.89413733 | C38: 0.49524631 | D38: 0.46177595 | F38: 7.9861111 | G38: -1.9001782
... A170: 144 | B170: 0.5950198 | C170: 0.054896522 | D170: 0.051186436 | F170: 99.652778 | G170: 5.5867023

Sheet SONIA, Swap, Credit
A1: SUMMARY OUTPUT
A3: Regression Statistics
A4: Multiple R | B4: 0.8203258
A5: R Square | B5: 0.67293442
A6: Adjusted R Square | B6: 0.66352246
A7: Standard Error | B7: 1.0839269
A8: Observations | B8: 144
A10: ANOVA
B11: df | C11: SS | D11: MS | E11: F | F11: Significance F
A12: Regression | B12: 4 | C12: 336.01037 | D12: 84.002591 | E12: 71.497805 | F12: 8.8362321e-33
A13: Residual | B13: 139 | C13: 163.31075 | D13: 1.1748975
A14: Total | B14: 143 | C14: 499.32112
B16: Coefficients | C16: Standard Error | D16: t Stat | E16: P-value | F16: Lower 95% | G16: Upper 95% | H16: Lower 95.0% | I16: Upper 95.0%
A17: Intercept | B17: 0.26395598 | C17: 0.12841012 | D17: 2.0555699 | E17: 0.041695801 | F17: 0.01006635 | G17: 0.51784562 | H17: 0.01006635 | I17: 0.51784562
A18: Average SONIA (%) | B18: 0.58981102 | C18: 0.5818455 | D18: 1.0136901 | E18: 0.31249191 | F18: -0.56060095 | G18: 1.740223 | H18: -0.56060095 | I18: 1.740223
A19: 3Y Gilt - 3Y OIS (%) | B19: -1.0693509 | C19: 4.8364574 | D19: -0.2211021 | E19: 0.82533739 | F19: -10.631887 | G19: 8.4931849 | H19: -10.631887 | I19: 8.4931849
A20: IG Credit Spread (%) | B20: 0.7969059 | C20: 0.048399683 | D20: 16.465106 | E20: 1.8267429e-34 | F20: 0.70121112 | G20: 0.89260067 | H20: 0.70121112 | I20: 0.89260067
A21: HY-IG Spread (%) | B21: 0.47072382 | C21: 0.059448241 | D21: 7.9182128 | E21: 6.9110924e-13 | F21: 0.35318408 | G21: 0.58826356 | H21: 0.35318408 | I21: 0.58826356
A25: RESIDUAL OUTPUT | F25: PROBABILITY OUTPUT
A27: Observation | B27: Predicted Asset Returns (%) | C27: Residuals | D27: Standard Residuals | F27: Percentile | G27: Asset Returns (%)
A28: 1 | B28: -1.0219997 | C28: -2.1011515 | D28: -1.9661561 | F28: 0.34722222 | G28: -7.0047285
A29: 2 | B29: 2.1372502 | C29: 1.301564 | D29: 1.2179407 | F29: 1.0416667 | G29: -4.6868599
A30: 3 | B30: -0.43522435 | C30: -1.4070933 | D30: -1.31669 | F30: 1.7361111 | G30: -4.1526948
A31: 4 | B31: 1.0759541 | C31: -0.31118884 | D31: -0.29119549 | F31: 2.4305556 | G31: -3.6875242
A32: 5 | B32: 2.0557723 | C32: 0.78808229 | D32: 0.73744935 | F32: 3.125 | G32: -3.3442886
A33: 6 | B33: -0.2280881 | C33: -0.17778593 | D33: -0.16636349 | F33: 3.8194444 | G33: -3.1231512
A34: 7 | B34: 0.26268109 | C34: 0.13195681 | D34: 0.12347881 | F34: 4.5138889 | G34: -2.9682787
A35: 8 | B35: 1.1449989 | C35: -1.9898664 | D35: -1.8620209 | F35: 5.2083333 | G35: -2.5680571
A36: 9 | B36: 1.1839455 | C36: 0.94811616 | D36: 0.88720132 | F36: 5.9027778 | G36: -2.5280473
A37: 10 | B37: 0.12221088 | C37: -0.54635099 | D37: -0.51124887 | F37: 6.5972222 | G37: -2.5046977
A38: 11 | B38: 0.9203459 | C38: -0.17514554 | D38: -0.16389274 | F38: 7.2916667 | G38: -2.2568119
A39: 12 | B39: 0.83257503 | C39: 0.55680861 | D39: 0.52103461 | F39: 7.9861111 | G39: -1.9001782
... A171: 144 | B171: 0.6386343 | C171: 0.011282021 | D171: 0.010557171 | F171: 99.652778 | G171: 5.5867023

Sheet Credit, VIX
A1: SUMMARY OUTPUT
A3: Regression Statistics
A4: Multiple R | B4: 0.82957255
A5: R Square | B5: 0.68819061
A6: Adjusted R Square | B6: 0.68150898
A7: Standard Error | B7: 1.0545582
A8: Observations | B8: 144
A10: ANOVA
B11: df | C11: SS | D11: MS | E11: F | F11: Significance F
A12: Regression | B12: 3 | C12: 343.6281 | D12: 114.5427 | E12: 102.99742 | F12: 2.9498272e-35
A13: Residual | B13: 140 | C13: 155.69301 | D13: 1.1120929
A14: Total | B14: 143 | C14: 499.32112
B16: Coefficients | C16: Standard Error | D16: t Stat | E16: P-value | F16: Lower 95% | G16: Upper 95% | H16: Lower 95.0% | I16: Upper 95.0%
A17: Intercept | B17: 1.1132794 | C17: 0.28358883 | D17: 3.9256816 | E17: 0.00013514631 | F17: 0.55260909 | G17: 1.6739498 | H17: 0.55260909 | I17: 1.6739498
A18: IG Credit Spread (%) | B18: 0.73523727 | C18: 0.051300464 | D18: 14.331981 | E18: 3.0535034e-29 | F18: 0.63381349 | G18: 0.83666104 | H18: 0.63381349 | I18: 0.83666104
A19: HY-IG Spread (%) | B19: 0.41479087 | C19: 0.061285314 | D19: 6.7681936 | E19: 3.2933992e-10 | F19: 0.29362651 | G19: 0.53595523 | H19: 0.29362651 | I19: 0.53595523
A20: VIX (Close) | B20: -0.041670892 | C20: 0.014723656 | D20: -2.8302001 | E20: 0.0053367803 | F20: -0.07078035 | G20: -0.012561433 | H20: -0.07078035 | I20: -0.012561433
A24: RESIDUAL OUTPUT | F24: PROBABILITY OUTPUT
A26: Observation | B26: Predicted Asset Returns (%) | C26: Residuals | D26: Standard Residuals | F26: Percentile | G26: Asset Returns (%)
A27: 1 | B27: -0.90278075 | C27: -2.2203705 | D27: -2.1279377 | F27: 0.34722222 | G27: -7.0047285
A28: 2 | B28: 2.2673056 | C28: 1.1715085 | D28: 1.1227393 | F28: 1.0416667 | G28: -4.6868599
A29: 3 | B29: -0.25609187 | C29: -1.5862258 | D29: -1.5201921 | F29: 1.7361111 | G29: -4.1526948
A30: 4 | B30: 1.1492581 | C30: -0.3844928 | D30: -0.36848657 | F30: 2.4305556 | G30: -3.6875242
A31: 5 | B31: 2.1720533 | C31: 0.67180133 | D31: 0.64383461 | F31: 3.125 | G31: -3.3442886
A32: 6 | B32: 0.050995098 | C32: -0.45686914 | D32: -0.43784992 | F32: 3.8194444 | G32: -3.1231512
A33: 7 | B33: 0.49615823 | C33: -0.10152033 | D33: -0.097294092 | F33: 4.5138889 | G33: -2.9682787
A34: 8 | B34: 1.1744204 | C34: -2.0192879 | D34: -1.9352261 | F34: 5.2083333 | G34: -2.5680571
A35: 9 | B35: 1.3284429 | C35: 0.80361877 | D35: 0.77016456 | F35: 5.9027778 | G35: -2.5280473
A36: 10 | B36: 0.38282967 | C36: -0.80696977 | D36: -0.77337606 | F36: 6.5972222 | G36: -2.5046977
A37: 11 | B37: 1.1544534 | C37: -0.40925305 | D37: -0.39221606 | F37: 7.2916667 | G37: -2.2568119
A38: 12 | B38: 1.1559983 | C38: 0.23338537 | D38: 0.22366966 | F38: 7.9861111 | G38: -1.9001782
... A170: 144 | B170: 0.67667332 | C170: -0.026756999 | D170: -0.025643119 | F170: 99.652778 | G170: 5.5867023

Sheet DSlope, DButterfly, Credit, VIX
A1: SUMMARY OUTPUT
A3: Regression Statistics
A4: Multiple R | B4: 0.82993455
A5: R Square | B5: 0.68879136
A6: Adjusted R Square | B6: 0.67751568
A7: Standard Error | B7: 1.0611487
A8: Observations | B8: 144
A10: ANOVA
B11: df | C11: SS | D11: MS | E11: F | F11: Significance F
A12: Regression | B12: 5 | C12: 343.92807 | D12: 68.785614 | E12: 61.086483 | F12: 2.6805237e-33
A13: Residual | B13: 138 | C13: 155.39305 | D13: 1.1260366
A14: Total | B14: 143 | C14: 499.32112
B16: Coefficients | C16: Standard Error | D16: t Stat | E16: P-value | F16: Lower 95% | G16: Upper 95% | H16: Lower 95.0% | I16: Upper 95.0%
A17: Intercept | B17: 1.1197811 | C17: 0.28800816 | D17: 3.8880187 | E17: 0.00015642852 | F17: 0.55030155 | G17: 1.6892607 | H17: 0.55030155 | I17: 1.6892607
A18: Slope Change (%) | B18: -1.071789 | C18: 6.1779263 | D18: -0.17348685 | E18: 0.86252298 | F18: -13.287424 | G18: 11.143847 | H18: -13.287424 | I18: 11.143847
A19: Butterfly Change (%) | B19: 5.4520342 | C19: 10.601973 | D19: 0.51424712 | E19: 0.60790176 | F19: -15.511285 | G19: 26.415353 | H19: -15.511285 | I19: 26.415353
A20: IG Credit Spread (%) | B20: 0.74128427 | C20: 0.053544032 | D20: 13.844386 | E20: 7.0993375e-28 | F20: 0.63541147 | G20: 0.84715708 | H20: 0.63541147 | I20: 0.84715708
A21: HY-IG Spread (%) | B21: 0.407765 | C21: 0.063270861 | D21: 6.444752 | E21: 1.7976839e-09 | F21: 0.28265931 | G21: 0.5328707 | H21: 0.28265931 | I21: 0.5328707
A22: VIX (Close) | B22: -0.041905715 | C22: 0.014928969 | D22: -2.8070065 | E22: 0.0057247201 | F22: -0.071424819 | G22: -0.012386611 | H22: -0.071424819 | I22: -0.012386611
A26: RESIDUAL OUTPUT | F26: PROBABILITY OUTPUT
A28: Observation | B28: Predicted Asset Returns (%) | C28: Residuals | D28: Standard Residuals | F28: Percentile | G28: Asset Returns (%)
A29: 1 | B29: -0.97477656 | C29: -2.1483747 | D29: -2.0609253 | F29: 0.34722222 | G29: -7.0047285
A30: 2 | B30: 2.2725519 | C30: 1.1662623 | D30: 1.1187897 | F30: 1.0416667 | G30: -4.6868599
A31: 3 | B31: -0.15245405 | C31: -1.6898636 | D31: -1.6210779 | F31: 1.7361111 | G31: -4.1526948
A32: 4 | B32: 1.1345939 | C32: -0.36982862 | D32: -0.35477479 | F32: 2.4305556 | G32: -3.6875242
A33: 5 | B33: 2.1687677 | C33: 0.6750869 | D33: 0.64760756 | F33: 3.125 | G33: -3.3442886
A34: 6 | B34: 0.087573765 | C34: -0.4934478 | D34: -0.47336206 | F34: 3.8194444 | G34: -3.1231512
A35: 7 | B35: 0.59237345 | C35: -0.19773554 | D35: -0.18968674 | F35: 4.5138889 | G35: -2.9682787
A36: 8 | B36: 1.0465842 | C36: -1.8914517 | D36: -1.8144603 | F36: 5.2083333 | G36: -2.5680571
A37: 9 | B37: 1.3415716 | C37: 0.79049003 | D37: 0.75831322 | F37: 5.9027778 | G37: -2.5280473
A38: 10 | B38: 0.34830691 | C38: -0.77244701 | D38: -0.74100463 | F38: 6.5972222 | G38: -2.5046977
A39: 11 | B39: 1.1392708 | C39: -0.39407048 | D39: -0.37802988 | F39: 7.2916667 | G39: -2.2568119
A40: 12 | B40: 1.1280267 | C40: 0.2613569 | D40: 0.2507184 | F40: 7.9861111 | G40: -1.9001782
... A172: 144 | B172: 0.69703108 | C172: -0.047114753 | D172: -0.045196952 | F172: 99.652778 | G172: 5.5867023

Sheet Credit, VIX, DInflation
A1: SUMMARY OUTPUT
A3: Regression Statistics
A4: Multiple R | B4: 0.83385559
A5: R Square | B5: 0.69531515
A6: Adjusted R Square | B6: 0.68654724
A7: Standard Error | B7: 1.0461838
A8: Observations | B8: 144
A10: ANOVA
B11: df | C11: SS | D11: MS | E11: F | F11: Significance F
A12: Regression | B12: 4 | C12: 347.18553 | D12: 86.796384 | E12: 79.302273 | F12: 6.6175453e-35
A13: Residual | B13: 139 | C13: 152.13558 | D13: 1.0945006
A14: Total | B14: 143 | C14: 499.32112
B16: Coefficients | C16: Standard Error | D16: t Stat | E16: P-value | F16: Lower 95% | G16: Upper 95% | H16: Lower 95.0% | I16: Upper 95.0%
A17: Intercept | B17: 1.1011112 | C17: 0.28141777 | D17: 3.9127281 | E17: 0.00014226893 | F17: 0.54469828 | G17: 1.6575242 | H17: 0.54469828 | I17: 1.6575242
A18: IG Credit Spread (%) | B18: 0.73348398 | C18: 0.050902373 | D18: 14.409623 | E18: 2.2756248e-29 | F18: 0.63284094 | G18: 0.83412702 | H18: 0.63284094 | I18: 0.83412702
A19: HY-IG Spread (%) | B19: 0.39305913 | C19: 0.06198206 | D19: 6.3414983 | E19: 2.9795791e-09 | F19: 0.27050958 | G19: 0.51560867 | H19: 0.27050958 | I19: 0.51560867
A20: VIX (Close) | B20: -0.040997456 | C20: 0.014611509 | D20: -2.8058331 | E20: 0.0057390722 | F20: -0.069887006 | G20: -0.012107906 | H20: -0.069887006 | I20: -0.012107906
A21: Inflation Change (%) | B21: 7.212295 | C21: 4.0004898 | D21: 1.802853 | E21: 0.07357769 | F21: -0.69738434 | G21: 15.121974 | H21: -0.69738434 | I21: 15.121974
A25: RESIDUAL OUTPUT | F25: PROBABILITY OUTPUT
A27: Observation | B27: Predicted Asset Returns (%) | C27: Residuals | D27: Standard Residuals | F27: Percentile | G27: Asset Returns (%)
A28: 1 | B28: -1.0210674 | C28: -2.1020838 | D28: -2.0379928 | F28: 0.34722222 | G28: -7.0047285
A29: 2 | B29: 2.404961 | C29: 1.0338532 | D29: 1.0023317 | F29: 1.0416667 | G29: -4.6868599
A30: 3 | B30: -0.18401784 | C30: -1.6582999 | D30: -1.6077395 | F30: 1.7361111 | G30: -4.1526948
A31: 4 | B31: 1.1464617 | C31: -0.38169639 | D31: -0.37005875 | F31: 2.4305556 | G31: -3.6875242
A32: 5 | B32: 2.2122079 | C32: 0.6316467 | D32: 0.61238825 | F32: 3.125 | G32: -3.3442886
A33: 6 | B33: -0.032073638 | C33: -0.3738004 | D33: -0.3624035 | F33: 3.8194444 | G33: -3.1231512
A34: 7 | B34: 0.54683303 | C34: -0.15219512 | D34: -0.14755481 | F34: 4.5138889 | G34: -2.9682787
A35: 8 | B35: 1.0937052 | C35: -1.9385727 | D35: -1.8794671 | F35: 5.2083333 | G35: -2.5680571
A36: 9 | B36: 1.3568955 | C36: 0.7751661 | D36: 0.75153185 | F36: 5.9027778 | G36: -2.5280473
A37: 10 | B37: 0.40684786 | C37: -0.83098797 | D37: -0.80565175 | F37: 6.5972222 | G37: -2.5046977
A38: 11 | B38: 1.2189185 | C38: -0.47371818 | D38: -0.45927486 | F38: 7.2916667 | G38: -2.2568119
A39: 12 | B39: 1.0813725 | C39: 0.30801109 | D39: 0.29862006 | F39: 7.9861111 | G39: -1.9001782
... A171: 144 | B171: 0.60707045 | C171: 0.042845869 | D171: 0.04153953 | F171: 99.652778 | G171: 5.5867023

Sheet Credit, VIX, DVIX, DInflation
A1: SUMMARY OUTPUT
A3: Regression Statistics
A4: Multiple R | B4: 0.8560243
A5: R Square | B5: 0.7327776
A6: Adjusted R Square | B6: 0.72309563
A7: Standard Error | B7: 0.98330184
A8: Observations | B8: 144
A10: ANOVA
B11: df | C11: SS | D11: MS | E11: F | F11: Significance F
A12: Regression | B12: 5 | C12: 365.89133 | D12: 73.178266 | E12: 75.684754 | F12: 7.9689543e-38
A13: Residual | B13: 138 | C13: 133.42979 | D13: 0.96688252
A14: Total | B14: 143 | C14: 499.32112
B16: Coefficients | C16: Standard Error | D16: t Stat | E16: P-value | F16: Lower 95% | G16: Upper 95% | H16: Lower 95.0% | I16: Upper 95.0%
A17: Intercept | B17: 0.80865963 | C17: 0.27273176 | D17: 2.9650365 | E17: 0.0035669277 | F17: 0.26938615 | G17: 1.3479331 | H17: 0.26938615 | I17: 1.3479331
A18: IG Credit Spread (%) | B18: 0.64314507 | C18: 0.052065114 | D18: 12.352706 | E18: 4.5049171e-24 | F18: 0.54019653 | G18: 0.7460936 | H18: 0.54019653 | I18: 0.7460936
A19: HY-IG Spread (%) | B19: 0.28518462 | C19: 0.063208596 | D19: 4.5118012 | E19: 1.3630784e-05 | F19: 0.16020204 | G19: 0.4101672 | H19: 0.16020204 | I19: 0.4101672
A20: VIX (Close) | B20: -0.02027169 | C20: 0.014519161 | D20: -1.3962026 | E20: 0.16489538 | F20: -0.048980479 | G20: 0.0084370982 | H20: -0.048980479 | I20: 0.0084370982
A21: Change in VIX (%) | B21: -0.016665359 | C21: 0.0037889029 | D21: -4.3984657 | E21: 2.162684e-05 | F21: -0.02415717 | G21: -0.0091735483 | H21: -0.02415717 | I21: -0.0091735483
A22: Inflation Change (%) | B22: 8.9336678 | C22: 3.7803483 | D22: 2.3631864 | E22: 0.01951381 | F22: 1.4587718 | G22: 16.408564 | H22: 1.4587718 | I22: 16.408564
A26: RESIDUAL OUTPUT | F26: PROBABILITY OUTPUT
A28: Observation | B28: Predicted Asset Returns (%) | C28: Residuals | D28: Standard Residuals | F28: Percentile | G28: Asset Returns (%)
A29: 1 | B29: -1.199588 | C29: -1.9235632 | D29: -1.9913522 | F29: 0.34722222 | G29: -7.0047285
A30: 2 | B30: 2.4996061 | C30: 0.93920805 | D30: 0.97230703 | F30: 1.0416667 | G30: -4.6868599
A31: 3 | B31: -0.75574984 | C31: -1.0865678 | D31: -1.12486 | F31: 1.7361111 | G31: -4.1526948
A32: 4 | B32: 1.0943941 | C32: -0.32962885 | D32: -0.34124543 | F32: 2.4305556 | G32: -3.6875242
A33: 5 | B33: 2.2952356 | C33: 0.54861903 | D33: 0.56795312 | F33: 3.125 | G33: -3.3442886
A34: 6 | B34: -0.12046386 | C34: -0.28541017 | D34: -0.29546842 | F34: 3.8194444 | G34: -3.1231512
A35: 7 | B35: 0.57538071 | C35: -0.1807428 | D35: -0.18711243 | F35: 4.5138889 | G35: -2.9682787
A36: 8 | B36: 0.58724596 | C36: -1.4321134 | D36: -1.4825831 | F36: 5.2083333 | G36: -2.5680571
A37: 9 | B37: 1.5808923 | C37: 0.55116937 | D37: 0.57059334 | F37: 5.9027778 | G37: -2.5280473
A38: 10 | B38: 0.44412087 | C38: -0.86826097 | D38: -0.89885968 | F38: 6.5972222 | G38: -2.5046977
A39: 11 | B39: 1.1438416 | C39: -0.39864127 | D39: -0.41268994 | F39: 7.2916667 | G39: -2.2568119
A40: 12 | B40: 1.1782394 | C40: 0.21114421 | D40: 0.21858522 | F40: 7.9861111 | G40: -1.9001782
... A172: 144 | B172: 0.70030981 | C172: -0.050393491 | D172: -0.052169427 | F172: 99.652778 | G172: 5.5867023

Sheet Credit, Dinflation, DVIX
A1: SUMMARY OUTPUT
A3: Regression Statistics
A4: Multiple R | B4: 0.85381662
A5: R Square | B5: 0.72900283
A6: Adjusted R Square | B6: 0.72120435
A7: Standard Error | B7: 0.98665415
A8: Observations | B8: 144
A10: ANOVA
B11: df | C11: SS | D11: MS | E11: F | F11: Significance F
A12: Regression | B12: 4 | C12: 364.0065 | D12: 91.001626 | E12: 93.48012 | F12: 2.0148981e-38
A13: Residual | B13: 139 | C13: 135.31461 | D13: 0.97348641
A14: Total | B14: 143 | C14: 499.32112
B16: Coefficients | C16: Standard Error | D16: t Stat | E16: P-value | F16: Lower 95% | G16: Upper 95% | H16: Lower 95.0% | I16: Upper 95.0%
A17: Intercept | B17: 0.44656557 | C17: 0.08469338 | D17: 5.2727329 | E17: 5.0242051e-07 | F17: 0.2791117 | G17: 0.61401943 | H17: 0.2791117 | I17: 0.61401943
A18: IG Credit Spread (%) | B18: 0.66044922 | C18: 0.050740885 | D18: 13.016116 | E18: 7.9697247e-26 | F18: 0.56012548 | G18: 0.76077297 | H18: 0.56012548 | I18: 0.76077297
A19: HY-IG Spread (%) | B19: 0.29893259 | C19: 0.062649784 | D19: 4.7714863 | E19: 4.5706558e-06 | F19: 0.17506283 | G19: 0.42280235 | H19: 0.17506283 | I19: 0.42280235
A20: Inflation Change (%) | B20: 9.2379453 | C20: 3.7869279 | D20: 2.4394299 | E20: 0.015970585 | F20: 1.7505158 | G20: 16.725375 | H20: 1.7505158 | I20: 16.725375
A21: Change in VIX (%) | B21: -0.018382199 | C21: 0.0035960355 | D21: -5.1117959 | E21: 1.0362051e-06 | F21: -0.0254922 | G21: -0.011272198 | H21: -0.0254922 | I21: -0.011272198
A25: RESIDUAL OUTPUT | F25: PROBABILITY OUTPUT
A27: Observation | B27: Predicted Asset Returns (%) | C27: Residuals | D27: Standard Residuals | F27: Percentile | G27: Asset Returns (%)
A28: 1 | B28: -1.2331369 | C28: -1.8900144 | D28: -1.9429462 | F28: 0.34722222 | G28: -7.0047285
A29: 2 | B29: 2.4856304 | C29: 0.9531838 | D29: 0.97987872 | F29: 1.0416667 | G29: -4.6868599
A30: 3 | B30: -0.86031769 | C30: -0.982 | D30: -1.0095019 | F30: 1.7361111 | G30: -4.1526948
A31: 4 | B31: 1.0874628 | C31: -0.32269758 | D31: -0.33173506 | F31: 2.4305556 | G31: -3.6875242
A32: 5 | B32: 2.2846001 | C32: 0.55925457 | D32: 0.57491708 | F32: 3.125 | G32: -3.3442886
A33: 6 | B33: -0.21888513 | C33: -0.1869889 | D33: -0.19222573 | F33: 3.8194444 | G33: -3.1231512
A34: 7 | B34: 0.5095784 | C34: -0.1149405 | D34: -0.11815953 | F34: 4.5138889 | G34: -2.9682787
A35: 8 | B35: 0.54824382 | C35: -1.3931113 | D35: -1.4321269 | F35: 5.2083333 | G35: -2.5680571
A36: 9 | B36: 1.5716552 | C36: 0.56040642 | D36: 0.57610119 | F36: 5.9027778 | G36: -2.5280473
A37: 10 | B37: 0.36445258 | C37: -0.78859268 | D37: -0.81067805 | F37: 6.5972222 | G37: -2.5046977
A38: 11 | B38: 1.0629259 | C38: -0.31772556 | D38: -0.3266238 | F38: 7.2916667 | G38: -2.2568119
A39: 12 | B39: 1.0730304 | C39: 0.31635325 | D39: 0.32521306 | F39: 7.9861111 | G39: -1.9001782
... A171: 144 | B171: 0.65512122 | C171: -0.0052048956 | D171: -0.0053506642 | F171: 99.652778 | G171: 5.5867023

Sheet S&P Returns on IG and HY
A1: SUMMARY OUTPUT
A3: Regression Statistics
A4: Multiple R | B4: 0.99786585
A5: R Square | B5: 0.99573625
A6: Adjusted R Square | B6: 0.99567577
A7: Standard Error | B7: 0.12730937
A8: Observations | B8: 144
A10: ANOVA
B11: df | C11: SS | D11: MS | E11: F | F11: Significance F
A12: Regression | B12: 2 | C12: 533.69384 | D12: 266.84692 | E12: 16464.23 | F12: 7.9494304e-168
A13: Residual | B13: 141 | C13: 2.2852824 | D13: 0.016207677
A14: Total | B14: 143 | C14: 535.97912
B16: Coefficients | C16: Standard Error | D16: t Stat | E16: P-value | F16: Lower 95% | G16: Upper 95% | H16: Lower 95.0% | I16: Upper 95.0%
A17: Intercept | B17: -0.14072406 | C17: 0.010656854 | D17: -13.205028 | E17: 2.0214022e-26 | F17: -0.16179193 | G17: -0.11965619 | H17: -0.16179193 | I17: -0.11965619
A18: IG Credit Spread (%) | B18: -0.98711481 | C18: 0.0056150387 | D18: -175.7984 | E18: 4.5815016e-167 | F18: -0.99821535 | G18: -0.97601426 | H18: -0.99821535 | I18: -0.97601426
A19: HY-IG Spread (%) | B19: -0.99336085 | C19: 0.0069720679 | D19: -142.47722 | E19: 2.8704579e-154 | F19: -1.0071442 | G19: -0.97957755 | H19: -1.0071442 | I19: -0.97957755
A23: RESIDUAL OUTPUT | F23: PROBABILITY OUTPUT
A25: Observation | B25: Predicted S&P 500 Returns - HY (%) | C25: Residuals | D25: Standard Residuals | F25: Percentile | G25: S&P 500 Returns - HY (%)
A26: 1 | B26: -0.9707723 | C26: 0.059807921 | D26: 0.47310419 | F26: 0.34722222 | G26: -6.414447
A27: 2 | B27: -2.4297733 | C27: 0.031759646 | D27: 0.25123129 | F27: 1.0416667 | G27: -5.4985096
A28: 3 | B28: 0.72694643 | C28: 0.023056317 | D28: 0.18238454 | F28: 1.7361111 | G28: -4.1583516
A29: 4 | B29: -1.2457214 | C29: 0.0088132858 | D29: 0.069716558 | F29: 2.4305556 | G29: -3.8039424
A30: 5 | B30: -2.4816751 | C30: 0.0056656418 | D30: 0.044817456 | F30: 3.125 | G30: -3.6270797
A31: 6 | B31: -0.053468358 | C31: 0.051745615 | D31: 0.40932817 | F31: 3.8194444 | G31: -3.4444537
A32: 7 | B32: -0.72468265 | C32: -0.0026321629 | D32: -0.020821444 | F32: 4.5138889 | G32: -3.2444939
A33: 8 | B33: -0.51157392 | C33: -0.0085425969 | D33: -0.067575302 | F33: 5.2083333 | G33: -3.2081608
A34: 9 | B34: -1.9075719 | C34: -0.018904015 | D34: -0.14953819 | F34: 5.9027778 | G34: -2.9162249
A35: 10 | B35: -0.01179419 | C35: 0.018712898 | D35: 0.14802638 | F35: 6.5972222 | G35: -2.8853567
A36: 11 | B36: -0.63185144 | C36: -0.018912291 | D36: -0.14960366 | F36: 7.2916667 | G36: -2.4760095
A37: 12 | B37: -0.51511091 | C37: 0.00021536765 | D37: 0.0017036428 | F37: 7.9861111 | G37: -2.3980136
... A169: 144 | B169: -0.41083836 | C169: -0.18125288 | D169: -1.4337816 | F169: 99.652778 | G169: 12.216042

Sheet Dinflation on Credit, SP-HY
A1: SUMMARY OUTPUT
A3: Regression Statistics
A4: Multiple R | B4: 0.29888629
A5: R Square | B5: 0.089333012
A6: Adjusted R Square | B6: 0.069818719
A7: Standard Error | B7: 0.021763751
A8: Observations | B8: 144
A10: ANOVA
B11: df | C11: SS | D11: MS | E11: F | F11: Significance F
A12: Regression | B12: 3 | C12: 0.0065050094 | D12: 0.0021683365 | E12: 4.5778248 | F12: 0.0043288435
A13: Residual | B13: 140 | C13: 0.066312522 | D13: 0.00047366087
A14: Total | B14: 143 | C14: 0.072817531
B16: Coefficients | C16: Standard Error | D16: t Stat | E16: P-value | F16: Lower 95% | G16: Upper 95% | H16: Lower 95.0% | I16: Upper 95.0%
A17: Intercept | B17: 0.0042659557 | C17: 0.0027246136 | D17: 1.5657103 | E17: 0.11967402 | F17: -0.0011207518 | G17: 0.0096526632 | H17: -0.0011207518 | I17: 0.0096526632
A18: IG Credit Spread (%) | B18: 0.030457987 | C18: 0.014243605 | D18: 2.1383621 | E18: 0.034223399 | F18: 0.0022976135 | G18: 0.05861836 | H18: 0.0022976135 | I18: 0.05861836
A19: HY-IG Spread (%) | B19: 0.033411158 | C19: 0.014350728 | D19: 2.3281856 | E19: 0.021334631 | F19: 0.0050389983 | G19: 0.061783318 | H19: 0.0050389983 | I19: 0.061783318
A20: S&P 500 Returns - HY (%) | B20: 0.030470255 | C20: 0.014396729 | D20: 2.1164707 | E20: 0.036074046 | F20: 0.0020071487 | G20: 0.05893336 | H20: 0.0020071487 | I20: 0.05893336
A24: RESIDUAL OUTPUT | E24: PROBABILITY OUTPUT
A26: Observation | B26: Predicted Inflation Change (%) | C26: Residuals | E26: Percentile | F26: Inflation Change (%)
A27: 1 | B27: 0.018522831 | C27: -0.018155698 | E27: 0.34722222 | F27: -0.11083333
A28: 2 | B28: 0.0017468042 | C28: 0.018253196 | E28: 1.0416667 | F28: -0.06
A29: 3 | B29: 0.00046750564 | C29: 0.0095324944 | E29: 1.7361111 | F29: -0.0575
A30: 4 | B30: 0.001481783 | C30: -0.00064844969 | E30: 2.4305556 | F30: -0.054166667
A31: 5 | B31: 0.002002611 | C31: 0.005497389 | E31: 3.125 | F31: -0.045
A32: 6 | B32: 0.0051417631 | C32: -0.012641763 | E32: 3.8194444 | F32: -0.043333333
A33: 7 | B33: 0.0042015556 | C33: 0.0074651111 | E33: 4.5138889 | F33: -0.035
A34: 8 | B34: -0.0048271149 | C34: -0.011006218 | E34: 5.2083333 | F34: -0.031666667
A35: 9 | B35: 0.0044765863 | C35: 0.0046900804 | E35: 5.9027778 | F35: -0.03
A36: 10 | B36: 0.00097429216 | C36: 0.0031923745 | E36: 6.5972222 | F36: -0.028333333
A37: 11 | B37: -0.0023973452 | C37: 0.0098973452 | E37: 7.2916667 | F37: -0.025833333
A38: 12 | B38: -0.0018997394 | C38: -0.0097669273 | E38: 7.9861111 | F38: -0.025
... A170: 144 | B170: -0.0053148746 | C170: -0.0038517921 | E170: 99.652778 | F170: 0.090833333
